{
  "matchInfo": {
    "id": "2i77risukcjigh8dhwe8pgxec",
    "coverageLevel": "13",
    "date": "2025-10-22Z",
    "time": "22:00:00Z",
    "localDate": "2025-10-22",
    "localTime": "18:00:00",
    "postMatch": "1",
    "numberOfPeriods": 2,
    "periodLength": 45,
    "overtimeLength": 15,
    "var": "1",
    "lastUpdated": "2025-11-26T16:42:17Z",
    "description": "Defence Force vs Mount Pleasant Academy",
    "sport": {
      "id": "289u5typ3vp4ifwh5thalohmq",
      "name": "Soccer"
    },
    "ruleset": {
      "id": "79plas4983031idr6vw83nuel",
      "name": "Men"
    },
    "competition": {
      "id": "e6ysw58xmvgh3zwg400zw565s",
      "name": "Concacaf Caribbean Cup",
      "knownName": "Concacaf Caribbean Cup",
      "competitionCode": "CAC",
      "competitionFormat": "International cup",
      "country": {
        "id": "7yfrmldo7ozpwui3n6wfcy1n9",
        "name": "N/C America"
      }
    },
    "tournamentCalendar": {
      "id": "bygi47fmsxgbzysjdf9u481lg",
      "startDate": "2025-08-20Z",
      "endDate": "2025-12-03Z",
      "name": "2025"
    },
    "stage": {
      "id": "bzzsolchg8eikhj2txyx4nims",
      "formatId": "2hrcobqge36fgp0q3wmc26f9x",
      "startDate": "2025-10-23Z",
      "endDate": "2025-11-07Z",
      "name": "Semi-finals"
    },
    "contestant": [
      {
        "id": "e9m9ysb5c4xf3b6yxmiq5cytx",
        "name": "Defence Force",
        "shortName": "Defence",
        "officialName": "Defence Force FC",
        "code": "DEF",
        "position": "home",
        "country": {
          "id": "635ed0499golbw7h62vt7g53j",
          "name": "Trinidad and Tobago"
        }
      },
      {
        "id": "34xm0flo8kh6skplqk4qybmui",
        "name": "Mount Pleasant Academy",
        "shortName": "Mt. Pleasant",
        "officialName": "Mount Pleasant Academy FC",
        "code": "MTP",
        "position": "away",
        "country": {
          "id": "gimxu1vjwoa2xrecyd9gtyoc",
          "name": "Jamaica"
        }
      }
    ],
    "venue": {
      "id": "b0n58s2p7z4lyzt8e6z4ryamk",
      "neutral": "no",
      "longName": "Hasely Crawford Stadium",
      "shortName": "Hasely Crawford Stadium",
      "latitude": "10.661504163",
      "longitude": "-61.533071995"
    }
  },
  "liveData": {
    "matchDetails": {
      "periodId": 14,
      "matchStatus": "Played",
      "winner": "away",
      "leg": 1,
      "relatedMatchId": "2j2eyie5rd7y7ct1blmb4naqc",
      "aggregateWinnerId": "34xm0flo8kh6skplqk4qybmui",
      "matchLengthMin": 102,
      "matchLengthSec": 17,
      "period": [
        {
          "id": 1,
          "start": "2025-10-22T22:08:28Z",
          "end": "2025-10-22T22:57:25Z",
          "lengthMin": 48,
          "lengthSec": 57,
          "announcedInjuryTime": 240
        },
        {
          "id": 2,
          "start": "2025-10-22T23:12:43Z",
          "end": "2025-10-23T00:06:03Z",
          "lengthMin": 53,
          "lengthSec": 20,
          "announcedInjuryTime": 480
        }
      ],
      "scores": {
        "ht": {
          "home": 0,
          "away": 2
        },
        "ft": {
          "home": 1,
          "away": 5
        },
        "total": {
          "home": 1,
          "away": 5
        },
        "aggregate": {
          "home": 2,
          "away": 5
        }
      }
    },
    "goal": [
      {
        "contestantId": "34xm0flo8kh6skplqk4qybmui",
        "periodId": 1,
        "timeMin": 5,
        "timeMinSec": "4:52",
        "lastUpdated": "2025-10-22T22:15:33Z",
        "timestamp": "2025-10-22T22:13:20Z",
        "type": "G",
        "scorerId": "edtj63dyxok9m949znhjh75sk",
        "scorerName": "W. Brown",
        "assistPlayerId": "19ycnmneiucdrc1fd9zwrf4rt",
        "assistPlayerName": "D. Green",
        "optaEventId": "2862690055",
        "homeScore": 0,
        "awayScore": 1,
        "varReviewed": "yes",
        "originalDecision": "Goal not awarded"
      },
      {
        "contestantId": "34xm0flo8kh6skplqk4qybmui",
        "periodId": 1,
        "timeMin": 15,
        "timeMinSec": "14:31",
        "lastUpdated": "2025-10-22T22:23:44Z",
        "timestamp": "2025-10-22T22:22:59Z",
        "type": "G",
        "scorerId": "6vsmcwxvz6hvbex8cxi6um1as",
        "scorerName": "R. Edwards",
        "assistPlayerId": "1m2glt59umfhzrf2kgdhppnmx",
        "assistPlayerName": "J. Topey",
        "optaEventId": "2862692813",
        "homeScore": 0,
        "awayScore": 2
      },
      {
        "contestantId": "34xm0flo8kh6skplqk4qybmui",
        "periodId": 2,
        "timeMin": 57,
        "timeMinSec": "56:58",
        "lastUpdated": "2025-10-22T23:25:34Z",
        "timestamp": "2025-10-22T23:24:42Z",
        "type": "G",
        "scorerId": "6vsmcwxvz6hvbex8cxi6um1as",
        "scorerName": "R. Edwards",
        "assistPlayerId": "edtj63dyxok9m949znhjh75sk",
        "assistPlayerName": "W. Brown",
        "secondAssistPlayerId": "854wvptw9qrm30peuykvmv2wa",
        "secondAssistPlayerName": "K. Bailey",
        "optaEventId": "2862710339",
        "homeScore": 0,
        "awayScore": 3
      },
      {
        "contestantId": "34xm0flo8kh6skplqk4qybmui",
        "periodId": 2,
        "timeMin": 85,
        "timeMinSec": "84:08",
        "lastUpdated": "2025-10-22T23:53:05Z",
        "timestamp": "2025-10-22T23:51:51Z",
        "type": "G",
        "scorerId": "7xbxhzaxnm9wwi8i0ww5nw67e",
        "scorerName": "S. Bradford",
        "assistPlayerId": "aci1ycl0srtdtrkrn8wsv0d0p",
        "assistPlayerName": "C. Walsh",
        "optaEventId": "2862719203",
        "homeScore": 0,
        "awayScore": 4
      },
      {
        "contestantId": "34xm0flo8kh6skplqk4qybmui",
        "periodId": 2,
        "timeMin": 93,
        "timeMinSec": "92:52",
        "lastUpdated": "2025-10-23T00:01:22Z",
        "timestamp": "2025-10-23T00:00:35Z",
        "type": "G",
        "scorerId": "854wvptw9qrm30peuykvmv2wa",
        "scorerName": "K. Bailey",
        "assistPlayerId": "4pcwwhx1q9z84bvlnl7rml05w",
        "assistPlayerName": "C. Thomas",
        "optaEventId": "2862722173",
        "homeScore": 0,
        "awayScore": 5
      },
      {
        "contestantId": "e9m9ysb5c4xf3b6yxmiq5cytx",
        "periodId": 2,
        "timeMin": 98,
        "timeMinSec": "97:01",
        "lastUpdated": "2025-10-23T08:26:31Z",
        "timestamp": "2025-10-23T00:04:44Z",
        "type": "G",
        "scorerId": "e84jqgpykkefdrxq7r1rrm13o",
        "scorerName": "K. Thomas",
        "optaEventId": "2862723465",
        "homeScore": 1,
        "awayScore": 5
      }
    ],
    "card": [
      {
        "contestantId": "e9m9ysb5c4xf3b6yxmiq5cytx",
        "periodId": 1,
        "timeMin": 18,
        "timeMinSec": "17:12",
        "lastUpdated": "2025-10-22T22:25:47Z",
        "timestamp": "2025-10-22T22:25:41Z",
        "type": "YC",
        "playerId": "7j2nikkbbz5b506j07wfmnget",
        "playerName": "C. Gonzales",
        "optaEventId": "2862693559",
        "cardReason": "Foul"
      },
      {
        "contestantId": "e9m9ysb5c4xf3b6yxmiq5cytx",
        "periodId": 1,
        "timeMin": 22,
        "timeMinSec": "21:14",
        "lastUpdated": "2025-10-22T22:29:48Z",
        "timestamp": "2025-10-22T22:29:43Z",
        "type": "YC",
        "playerId": "5jlxcjvtt4ezrb4x4mtpv11t6",
        "playerName": "T. Bailey",
        "optaEventId": "2862694795",
        "cardReason": "Foul"
      },
      {
        "contestantId": "e9m9ysb5c4xf3b6yxmiq5cytx",
        "periodId": 2,
        "timeMin": 50,
        "timeMinSec": "49:55",
        "lastUpdated": "2025-10-22T23:17:47Z",
        "timestamp": "2025-10-22T23:17:38Z",
        "type": "YC",
        "playerId": "33ym8s4p1pr2yednzer7z482x",
        "playerName": "S. Bertrand",
        "optaEventId": "2862708391",
        "cardReason": "Foul"
      },
      {
        "contestantId": "e9m9ysb5c4xf3b6yxmiq5cytx",
        "periodId": 2,
        "timeMin": 67,
        "timeMinSec": "66:20",
        "lastUpdated": "2025-10-22T23:34:12Z",
        "timestamp": "2025-10-22T23:34:03Z",
        "type": "YC",
        "playerId": "3z982g6djrv6piwca4gm91ln9",
        "playerName": "S. Bateau",
        "optaEventId": "2862713285",
        "cardReason": "Foul"
      },
      {
        "contestantId": "34xm0flo8kh6skplqk4qybmui",
        "periodId": 2,
        "timeMin": 78,
        "timeMinSec": "77:24",
        "lastUpdated": "2025-10-22T23:45:18Z",
        "timestamp": "2025-10-22T23:45:07Z",
        "type": "YC",
        "playerId": "aci1ycl0srtdtrkrn8wsv0d0p",
        "playerName": "C. Walsh",
        "optaEventId": "2862716735",
        "cardReason": "Foul"
      },
      {
        "contestantId": "e9m9ysb5c4xf3b6yxmiq5cytx",
        "periodId": 2,
        "timeMin": 82,
        "timeMinSec": "81:32",
        "lastUpdated": "2025-10-22T23:49:23Z",
        "timestamp": "2025-10-22T23:49:15Z",
        "type": "YC",
        "playerId": "35r9p11v6zgsly9kytci0xroq",
        "playerName": "J. Sadoo",
        "optaEventId": "2862718235",
        "cardReason": "Foul"
      }
    ],
    "substitute": [
      {
        "contestantId": "e9m9ysb5c4xf3b6yxmiq5cytx",
        "periodId": 2,
        "timeMin": 61,
        "timeMinSec": "60:48",
        "lastUpdated": "2025-10-22T23:28:47Z",
        "timestamp": "2025-10-22T23:28:31Z",
        "playerOnId": "5nqdfyqynck5i7pgdgc5rqgpg",
        "playerOnName": "E. Seechan",
        "playerOffId": "5jlxcjvtt4ezrb4x4mtpv11t6",
        "playerOffName": "T. Bailey",
        "subReason": "Tactical"
      },
      {
        "contestantId": "e9m9ysb5c4xf3b6yxmiq5cytx",
        "periodId": 2,
        "timeMin": 61,
        "timeMinSec": "60:52",
        "lastUpdated": "2025-10-22T23:28:41Z",
        "timestamp": "2025-10-22T23:28:35Z",
        "playerOnId": "7es2qglg6om38fvi8hhvltroq",
        "playerOnName": "R. Coryat",
        "playerOffId": "2un2xqr20t1nhci2jfk66s73d",
        "playerOffName": "C. Keller",
        "subReason": "Tactical"
      },
      {
        "contestantId": "34xm0flo8kh6skplqk4qybmui",
        "periodId": 2,
        "timeMin": 62,
        "timeMinSec": "61:18",
        "lastUpdated": "2025-10-22T23:29:08Z",
        "timestamp": "2025-10-22T23:29:01Z",
        "playerOnId": "5nz5i26odqajveymm7s84ybfu",
        "playerOnName": "G. Irving",
        "playerOffId": "19ycnmneiucdrc1fd9zwrf4rt",
        "playerOffName": "D. Green",
        "subReason": "Tactical"
      },
      {
        "contestantId": "e9m9ysb5c4xf3b6yxmiq5cytx",
        "periodId": 2,
        "timeMin": 71,
        "timeMinSec": "70:53",
        "lastUpdated": "2025-10-22T23:38:43Z",
        "timestamp": "2025-10-22T23:38:36Z",
        "playerOnId": "35r9p11v6zgsly9kytci0xroq",
        "playerOnName": "J. Sadoo",
        "playerOffId": "24a2k1eq8actrhhv7avvdemz9",
        "playerOffName": "K. Goddard",
        "subReason": "Tactical"
      },
      {
        "contestantId": "e9m9ysb5c4xf3b6yxmiq5cytx",
        "periodId": 2,
        "timeMin": 71,
        "timeMinSec": "70:59",
        "lastUpdated": "2025-10-22T23:38:51Z",
        "timestamp": "2025-10-22T23:38:42Z",
        "playerOnId": "25qh119aybpz97j7wvh9xy7s9",
        "playerOnName": "J. Felix",
        "playerOffId": "akl7hh6enqya75c3umeoo6xas",
        "playerOffName": "J. Araujo-Wilson",
        "subReason": "Tactical"
      },
      {
        "contestantId": "34xm0flo8kh6skplqk4qybmui",
        "periodId": 2,
        "timeMin": 75,
        "timeMinSec": "74:21",
        "lastUpdated": "2025-10-22T23:42:12Z",
        "timestamp": "2025-10-22T23:42:04Z",
        "playerOnId": "7xbxhzaxnm9wwi8i0ww5nw67e",
        "playerOnName": "S. Bradford",
        "playerOffId": "549bk4ar8s05kzy78wi86one2",
        "playerOffName": "A. Marshsall",
        "subReason": "Tactical"
      },
      {
        "contestantId": "34xm0flo8kh6skplqk4qybmui",
        "periodId": 2,
        "timeMin": 75,
        "timeMinSec": "74:30",
        "lastUpdated": "2025-10-22T23:42:20Z",
        "timestamp": "2025-10-22T23:42:13Z",
        "playerOnId": "aci1ycl0srtdtrkrn8wsv0d0p",
        "playerOnName": "C. Walsh",
        "playerOffId": "edtj63dyxok9m949znhjh75sk",
        "playerOffName": "W. Brown",
        "subReason": "Tactical"
      },
      {
        "contestantId": "34xm0flo8kh6skplqk4qybmui",
        "periodId": 2,
        "timeMin": 75,
        "timeMinSec": "74:46",
        "lastUpdated": "2025-10-22T23:42:35Z",
        "timestamp": "2025-10-22T23:42:29Z",
        "playerOnId": "11fnw0grmhiwnqc6xg7xjlasp",
        "playerOnName": "T. Shaw",
        "playerOffId": "6vsmcwxvz6hvbex8cxi6um1as",
        "playerOffName": "R. Edwards",
        "subReason": "Tactical"
      },
      {
        "contestantId": "e9m9ysb5c4xf3b6yxmiq5cytx",
        "periodId": 2,
        "timeMin": 76,
        "timeMinSec": "75:02",
        "lastUpdated": "2025-10-22T23:42:51Z",
        "timestamp": "2025-10-22T23:42:45Z",
        "playerOnId": "5asx9pvxtu0o4byij9kv83cic",
        "playerOnName": "R. Francois",
        "playerOffId": "3z982g6djrv6piwca4gm91ln9",
        "playerOffName": "S. Bateau",
        "subReason": "Tactical"
      },
      {
        "contestantId": "34xm0flo8kh6skplqk4qybmui",
        "periodId": 2,
        "timeMin": 83,
        "timeMinSec": "82:34",
        "lastUpdated": "2025-10-22T23:50:23Z",
        "timestamp": "2025-10-22T23:50:17Z",
        "playerOnId": "2py7ki0xiqxg8aovuuwh3bxn8",
        "playerOnName": "C. Nugent",
        "playerOffId": "61esp7ett8p66f2agq9nuryp6",
        "playerOffName": "J. Anglin",
        "subReason": "Tactical"
      }
    ],
    "VAR": [
      {
        "contestantId": "34xm0flo8kh6skplqk4qybmui",
        "periodId": 1,
        "timeMin": 6,
        "timeMinSec": "5:56",
        "lastUpdated": "2025-10-22T22:14:38Z",
        "timestamp": "2025-10-22T22:14:18Z",
        "type": "Goal not awarded",
        "decision": "Cancelled",
        "outcome": "Goal",
        "playerId": "edtj63dyxok9m949znhjh75sk",
        "playerName": "W. Brown",
        "optaEventId": "2862689975"
      }
    ],
    "lineUp": [
      {
        "contestantId": "e9m9ysb5c4xf3b6yxmiq5cytx",
        "formationUsed": "4231",
        "player": [
          {
            "playerId": "c5qi5cy84czzlexmdcysi61ux",
            "firstName": "Christopher Jerani",
            "lastName": "Biggette",
            "shortFirstName": "Christopher",
            "shortLastName": "Biggette",
            "matchName": "C. Biggette",
            "shirtNumber": 22,
            "position": "Goalkeeper",
            "positionSide": "Centre",
            "formationPlace": "1",
            "stat": [
              {
                "type": "accuratePass",
                "value": "23"
              },
              {
                "type": "gameStarted",
                "value": "1"
              },
              {
                "type": "goalKicks",
                "value": "7"
              },
              {
                "type": "goalsConceded",
                "value": "5"
              },
              {
                "type": "lostCorners",
                "value": "1"
              },
              {
                "type": "minsPlayed",
                "value": "90"
              },
              {
                "type": "saves",
                "value": "4"
              },
              {
                "type": "totalClearance",
                "value": "1"
              },
              {
                "type": "totalPass",
                "value": "27"
              },
              {
                "type": "formationPlace",
                "value": "1"
              }
            ]
          },
          {
            "playerId": "akl7hh6enqya75c3umeoo6xas",
            "firstName": "Joshua James",
            "lastName": "Araujo-Wilson",
            "shortFirstName": "Joshua",
            "shortLastName": "Araujo-Wilson",
            "matchName": "J. Araujo-Wilson",
            "shirtNumber": 4,
            "position": "Defender",
            "positionSide": "Left",
            "formationPlace": "3",
            "stat": [
              {
                "type": "accuratePass",
                "value": "21"
              },
              {
                "type": "gameStarted",
                "value": "1"
              },
              {
                "type": "goalKicks",
                "value": "1"
              },
              {
                "type": "goalsConceded",
                "value": "3"
              },
              {
                "type": "minsPlayed",
                "value": "71"
              },
              {
                "type": "totalPass",
                "value": "25"
              },
              {
                "type": "totalSubOff",
                "value": "1"
              },
              {
                "type": "totalTackle",
                "value": "2"
              },
              {
                "type": "totalThrows",
                "value": "4"
              },
              {
                "type": "wonTackle",
                "value": "1"
              },
              {
                "type": "formationPlace",
                "value": "3"
              }
            ]
          },
          {
            "playerId": "7j2nikkbbz5b506j07wfmnget",
            "firstName": "Curtis Kareem",
            "lastName": "Gonzales",
            "shortFirstName": "Curtis",
            "shortLastName": "Gonzales",
            "matchName": "C. Gonzales",
            "shirtNumber": 17,
            "position": "Defender",
            "positionSide": "Left/Centre",
            "formationPlace": "6",
            "stat": [
              {
                "type": "accuratePass",
                "value": "61"
              },
              {
                "type": "fouls",
                "value": "1"
              },
              {
                "type": "gameStarted",
                "value": "1"
              },
              {
                "type": "goalsConceded",
                "value": "5"
              },
              {
                "type": "minsPlayed",
                "value": "90"
              },
              {
                "type": "totalClearance",
                "value": "4"
              },
              {
                "type": "totalPass",
                "value": "71"
              },
              {
                "type": "wasFouled",
                "value": "2"
              },
              {
                "type": "yellowCard",
                "value": "1"
              },
              {
                "type": "formationPlace",
                "value": "6"
              }
            ]
          },
          {
            "playerId": "3z982g6djrv6piwca4gm91ln9",
            "firstName": "Sheldon Michael Louis",
            "lastName": "Bateau",
            "shortFirstName": "Sheldon",
            "shortLastName": "Bateau",
            "matchName": "S. Bateau",
            "shirtNumber": 8,
            "position": "Defender",
            "positionSide": "Centre/Right",
            "formationPlace": "5",
            "stat": [
              {
                "type": "accuratePass",
                "value": "24"
              },
              {
                "type": "fouls",
                "value": "2"
              },
              {
                "type": "gameStarted",
                "value": "1"
              },
              {
                "type": "goalsConceded",
                "value": "3"
              },
              {
                "type": "lostCorners",
                "value": "2"
              },
              {
                "type": "minsPlayed",
                "value": "76"
              },
              {
                "type": "totalClearance",
                "value": "8"
              },
              {
                "type": "totalPass",
                "value": "27"
              },
              {
                "type": "totalSubOff",
                "value": "1"
              },
              {
                "type": "totalTackle",
                "value": "1"
              },
              {
                "type": "wonTackle",
                "value": "1"
              },
              {
                "type": "yellowCard",
                "value": "1"
              },
              {
                "type": "formationPlace",
                "value": "5"
              }
            ]
          },
          {
            "playerId": "f11g45ggbyb6byatntlbtnrx0",
            "firstName": "Christian Omario",
            "lastName": "Bailey",
            "shortFirstName": "Christian",
            "shortLastName": "Bailey",
            "matchName": "C. Bailey",
            "shirtNumber": 28,
            "position": "Defender",
            "positionSide": "Right",
            "formationPlace": "2",
            "stat": [
              {
                "type": "accuratePass",
                "value": "33"
              },
              {
                "type": "fouls",
                "value": "1"
              },
              {
                "type": "gameStarted",
                "value": "1"
              },
              {
                "type": "goalsConceded",
                "value": "5"
              },
              {
                "type": "minsPlayed",
                "value": "90"
              },
              {
                "type": "totalClearance",
                "value": "3"
              },
              {
                "type": "totalPass",
                "value": "45"
              },
              {
                "type": "totalTackle",
                "value": "2"
              },
              {
                "type": "totalThrows",
                "value": "5"
              },
              {
                "type": "wonTackle",
                "value": "2"
              },
              {
                "type": "formationPlace",
                "value": "2"
              }
            ]
          },
          {
            "playerId": "24a2k1eq8actrhhv7avvdemz9",
            "firstName": "Kevon",
            "lastName": "Goddard",
            "shortFirstName": "Kevon",
            "shortLastName": "Goddard",
            "matchName": "K. Goddard",
            "shirtNumber": 6,
            "position": "Defensive Midfielder",
            "positionSide": "Left/Centre",
            "formationPlace": "4",
            "stat": [
              {
                "type": "accuratePass",
                "value": "31"
              },
              {
                "type": "fouls",
                "value": "2"
              },
              {
                "type": "gameStarted",
                "value": "1"
              },
              {
                "type": "goalsConceded",
                "value": "3"
              },
              {
                "type": "minsPlayed",
                "value": "71"
              },
              {
                "type": "totalPass",
                "value": "34"
              },
              {
                "type": "totalSubOff",
                "value": "1"
              },
              {
                "type": "wasFouled",
                "value": "1"
              },
              {
                "type": "formationPlace",
                "value": "4"
              }
            ]
          },
          {
            "playerId": "2un2xqr20t1nhci2jfk66s73d",
            "firstName": "Cassim Atiba",
            "lastName": "Kellar",
            "shortFirstName": "Cassim",
            "shortLastName": "Keller",
            "matchName": "C. Keller",
            "shirtNumber": 37,
            "position": "Defensive Midfielder",
            "positionSide": "Centre/Right",
            "formationPlace": "8",
            "stat": [
              {
                "type": "accuratePass",
                "value": "26"
              },
              {
                "type": "fouls",
                "value": "1"
              },
              {
                "type": "gameStarted",
                "value": "1"
              },
              {
                "type": "goalsConceded",
                "value": "3"
              },
              {
                "type": "minsPlayed",
                "value": "61"
              },
              {
                "type": "totalPass",
                "value": "29"
              },
              {
                "type": "totalSubOff",
                "value": "1"
              },
              {
                "type": "totalTackle",
                "value": "2"
              },
              {
                "type": "wasFouled",
                "value": "1"
              },
              {
                "type": "wonTackle",
                "value": "2"
              },
              {
                "type": "formationPlace",
                "value": "8"
              }
            ]
          },
          {
            "playerId": "5jlxcjvtt4ezrb4x4mtpv11t6",
            "firstName": "Tyrese",
            "lastName": "Bailey",
            "shortFirstName": "Tyrese",
            "shortLastName": "Bailey",
            "matchName": "T. Bailey",
            "shirtNumber": 45,
            "position": "Attacking Midfielder",
            "positionSide": "Left",
            "formationPlace": "11",
            "stat": [
              {
                "type": "accuratePass",
                "value": "14"
              },
              {
                "type": "fouls",
                "value": "1"
              },
              {
                "type": "gameStarted",
                "value": "1"
              },
              {
                "type": "goalsConceded",
                "value": "3"
              },
              {
                "type": "minsPlayed",
                "value": "61"
              },
              {
                "type": "totalPass",
                "value": "16"
              },
              {
                "type": "totalSubOff",
                "value": "1"
              },
              {
                "type": "totalTackle",
                "value": "2"
              },
              {
                "type": "wasFouled",
                "value": "1"
              },
              {
                "type": "wonTackle",
                "value": "1"
              },
              {
                "type": "yellowCard",
                "value": "1"
              },
              {
                "type": "formationPlace",
                "value": "11"
              }
            ]
          },
          {
            "playerId": "7kcezh1c08cnm02b13y5y20gl",
            "firstName": "Kevin Reginald",
            "lastName": "Molino",
            "shortFirstName": "Kevin",
            "shortLastName": "Molino",
            "matchName": "K. Molino",
            "shirtNumber": 10,
            "position": "Attacking Midfielder",
            "positionSide": "Centre",
            "formationPlace": "10",
            "captain": "yes",
            "stat": [
              {
                "type": "accuratePass",
                "value": "53"
              },
              {
                "type": "cornerTaken",
                "value": "1"
              },
              {
                "type": "gameStarted",
                "value": "1"
              },
              {
                "type": "goalsConceded",
                "value": "5"
              },
              {
                "type": "minsPlayed",
                "value": "90"
              },
              {
                "type": "ontargetScoringAtt",
                "value": "1"
              },
              {
                "type": "shotOffTarget",
                "value": "1"
              },
              {
                "type": "totalPass",
                "value": "69"
              },
              {
                "type": "totalScoringAtt",
                "value": "2"
              },
              {
                "type": "totalTackle",
                "value": "2"
              },
              {
                "type": "totalThrows",
                "value": "2"
              },
              {
                "type": "wasFouled",
                "value": "4"
              },
              {
                "type": "wonTackle",
                "value": "1"
              },
              {
                "type": "formationPlace",
                "value": "10"
              }
            ]
          },
          {
            "playerId": "e84jqgpykkefdrxq7r1rrm13o",
            "firstName": "Kaihim Torell Jaihem",
            "lastName": "Thomas",
            "shortFirstName": "Kaihim",
            "shortLastName": "Thomas",
            "matchName": "K. Thomas",
            "shirtNumber": 11,
            "position": "Attacking Midfielder",
            "positionSide": "Right",
            "formationPlace": "7",
            "stat": [
              {
                "type": "accuratePass",
                "value": "13"
              },
              {
                "type": "blockedScoringAtt",
                "value": "1"
              },
              {
                "type": "fouls",
                "value": "2"
              },
              {
                "type": "gameStarted",
                "value": "1"
              },
              {
                "type": "goals",
                "value": "1"
              },
              {
                "type": "goalsConceded",
                "value": "5"
              },
              {
                "type": "minsPlayed",
                "value": "90"
              },
              {
                "type": "ontargetScoringAtt",
                "value": "2"
              },
              {
                "type": "shotOffTarget",
                "value": "2"
              },
              {
                "type": "totalOffside",
                "value": "1"
              },
              {
                "type": "totalPass",
                "value": "16"
              },
              {
                "type": "totalScoringAtt",
                "value": "5"
              },
              {
                "type": "totalTackle",
                "value": "1"
              },
              {
                "type": "totalThrows",
                "value": "4"
              },
              {
                "type": "wasFouled",
                "value": "1"
              },
              {
                "type": "formationPlace",
                "value": "7"
              }
            ]
          },
          {
            "playerId": "33ym8s4p1pr2yednzer7z482x",
            "firstName": "Shaquille Shaval",
            "lastName": "Bertrand",
            "shortFirstName": "Shaquille",
            "shortLastName": "Bertrand",
            "matchName": "S. Bertrand",
            "shirtNumber": 15,
            "position": "Striker",
            "positionSide": "Centre",
            "formationPlace": "9",
            "stat": [
              {
                "type": "accuratePass",
                "value": "17"
              },
              {
                "type": "blockedScoringAtt",
                "value": "1"
              },
              {
                "type": "fouls",
                "value": "1"
              },
              {
                "type": "gameStarted",
                "value": "1"
              },
              {
                "type": "goalsConceded",
                "value": "5"
              },
              {
                "type": "minsPlayed",
                "value": "90"
              },
              {
                "type": "shotOffTarget",
                "value": "1"
              },
              {
                "type": "totalOffside",
                "value": "1"
              },
              {
                "type": "totalPass",
                "value": "22"
              },
              {
                "type": "totalScoringAtt",
                "value": "2"
              },
              {
                "type": "totalTackle",
                "value": "1"
              },
              {
                "type": "totalThrows",
                "value": "1"
              },
              {
                "type": "wasFouled",
                "value": "1"
              },
              {
                "type": "wonTackle",
                "value": "1"
              },
              {
                "type": "yellowCard",
                "value": "1"
              },
              {
                "type": "formationPlace",
                "value": "9"
              }
            ]
          },
          {
            "playerId": "c80fw1nrnzsqc8aqkm13pvey2",
            "firstName": "Jameel Jason James",
            "lastName": "Cooper",
            "shortFirstName": "Jameel",
            "shortLastName": "Cooper",
            "matchName": "J. Cooper",
            "shirtNumber": 32,
            "position": "Substitute",
            "subPosition": "Midfielder",
            "stat": [
              {
                "type": "formationPlace",
                "value": "0"
              }
            ]
          },
          {
            "playerId": "7es2qglg6om38fvi8hhvltroq",
            "firstName": "Rivaldo Antonio",
            "lastName": "Coryat",
            "shortFirstName": "Rivaldo",
            "shortLastName": "Coryat",
            "matchName": "R. Coryat",
            "shirtNumber": 13,
            "position": "Substitute",
            "subPosition": "Midfielder",
            "stat": [
              {
                "type": "accuratePass",
                "value": "15"
              },
              {
                "type": "blockedScoringAtt",
                "value": "1"
              },
              {
                "type": "goalsConceded",
                "value": "2"
              },
              {
                "type": "minsPlayed",
                "value": "29"
              },
              {
                "type": "totalPass",
                "value": "24"
              },
              {
                "type": "totalScoringAtt",
                "value": "1"
              },
              {
                "type": "totalSubOn",
                "value": "1"
              },
              {
                "type": "totalTackle",
                "value": "1"
              },
              {
                "type": "wasFouled",
                "value": "1"
              },
              {
                "type": "wonTackle",
                "value": "1"
              },
              {
                "type": "formationPlace",
                "value": "0"
              }
            ]
          },
          {
            "playerId": "25qh119aybpz97j7wvh9xy7s9",
            "firstName": "Jelani Jeriel Michael",
            "lastName": "Felix",
            "shortFirstName": "Jelani",
            "shortLastName": "Felix",
            "matchName": "J. Felix",
            "shirtNumber": 7,
            "position": "Substitute",
            "subPosition": "Defender",
            "stat": [
              {
                "type": "accuratePass",
                "value": "9"
              },
              {
                "type": "fouls",
                "value": "1"
              },
              {
                "type": "goalsConceded",
                "value": "2"
              },
              {
                "type": "lostCorners",
                "value": "1"
              },
              {
                "type": "minsPlayed",
                "value": "19"
              },
              {
                "type": "totalClearance",
                "value": "1"
              },
              {
                "type": "totalPass",
                "value": "13"
              },
              {
                "type": "totalSubOn",
                "value": "1"
              },
              {
                "type": "totalThrows",
                "value": "2"
              },
              {
                "type": "formationPlace",
                "value": "0"
              }
            ]
          },
          {
            "playerId": "5asx9pvxtu0o4byij9kv83cic",
            "firstName": "Russell Ronald",
            "lastName": "Francois",
            "shortFirstName": "Russell",
            "shortLastName": "Francois",
            "matchName": "R. Francois",
            "shirtNumber": 25,
            "position": "Substitute",
            "subPosition": "Defender",
            "stat": [
              {
                "type": "accuratePass",
                "value": "10"
              },
              {
                "type": "blockedScoringAtt",
                "value": "1"
              },
              {
                "type": "goalsConceded",
                "value": "2"
              },
              {
                "type": "minsPlayed",
                "value": "14"
              },
              {
                "type": "totalPass",
                "value": "10"
              },
              {
                "type": "totalScoringAtt",
                "value": "1"
              },
              {
                "type": "totalSubOn",
                "value": "1"
              },
              {
                "type": "wonCorners",
                "value": "1"
              },
              {
                "type": "formationPlace",
                "value": "0"
              }
            ]
          },
          {
            "playerId": "3id1gxybf1bxd6qkdhzgs7eqy",
            "firstName": "Adriel",
            "lastName": "George",
            "shortFirstName": "Adriel",
            "shortLastName": "George",
            "matchName": "A. George",
            "shirtNumber": 20,
            "position": "Substitute",
            "subPosition": "Midfielder",
            "stat": [
              {
                "type": "formationPlace",
                "value": "0"
              }
            ]
          },
          {
            "playerId": "n1g2xwebfodsr96jclmvf9qs",
            "firstName": "Isaiah Israel",
            "lastName": "Leacock",
            "shortFirstName": "Isaiah",
            "shortLastName": "Leacock",
            "matchName": "I. Leacock",
            "shirtNumber": 12,
            "position": "Substitute",
            "subPosition": "Attacker",
            "stat": [
              {
                "type": "formationPlace",
                "value": "0"
              }
            ]
          },
          {
            "playerId": "2m6tlqmxe9nlq9enntx9an1n8",
            "firstName": "Shirwin Zaka",
            "lastName": "Noel",
            "shortFirstName": "Shirwin",
            "shortLastName": "Noel",
            "matchName": "S. Noel",
            "shirtNumber": 33,
            "position": "Substitute",
            "subPosition": "Defender",
            "stat": [
              {
                "type": "formationPlace",
                "value": "0"
              }
            ]
          },
          {
            "playerId": "945ckzgkmh6iokp6d7rpwy5lh",
            "firstName": "Dwight",
            "lastName": "Quintero",
            "shortFirstName": "Dwight",
            "shortLastName": "Quintero",
            "matchName": "D. Quintero",
            "shirtNumber": 29,
            "position": "Substitute",
            "subPosition": "Attacker",
            "stat": [
              {
                "type": "formationPlace",
                "value": "0"
              }
            ]
          },
          {
            "playerId": "35r9p11v6zgsly9kytci0xroq",
            "firstName": "Justin Darius",
            "lastName": "Sadoo",
            "shortFirstName": "Justin",
            "shortLastName": "Sadoo",
            "matchName": "J. Sadoo",
            "shirtNumber": 21,
            "position": "Substitute",
            "subPosition": "Midfielder",
            "stat": [
              {
                "type": "accuratePass",
                "value": "20"
              },
              {
                "type": "fouls",
                "value": "1"
              },
              {
                "type": "goalsConceded",
                "value": "2"
              },
              {
                "type": "minsPlayed",
                "value": "19"
              },
              {
                "type": "totalPass",
                "value": "21"
              },
              {
                "type": "totalSubOn",
                "value": "1"
              },
              {
                "type": "yellowCard",
                "value": "1"
              },
              {
                "type": "formationPlace",
                "value": "0"
              }
            ]
          },
          {
            "playerId": "5nqdfyqynck5i7pgdgc5rqgpg",
            "firstName": "Elijah",
            "lastName": "Seechan",
            "shortFirstName": "Elijah",
            "shortLastName": "Seechan",
            "matchName": "E. Seechan",
            "shirtNumber": 18,
            "position": "Substitute",
            "subPosition": "Attacker",
            "stat": [
              {
                "type": "accuratePass",
                "value": "6"
              },
              {
                "type": "goalsConceded",
                "value": "2"
              },
              {
                "type": "minsPlayed",
                "value": "29"
              },
              {
                "type": "totalPass",
                "value": "6"
              },
              {
                "type": "totalSubOn",
                "value": "1"
              },
              {
                "type": "wasFouled",
                "value": "1"
              },
              {
                "type": "formationPlace",
                "value": "0"
              }
            ]
          },
          {
            "playerId": "26d37faltf4zz4ue71lspabmy",
            "firstName": "Jabari Dimitri Anthony",
            "lastName": "St. Hillaire",
            "shortFirstName": "Jabari",
            "shortLastName": "St Hillaire",
            "knownName": "Jabari St Hillaire",
            "matchName": "J. St. Hillaire",
            "shirtNumber": 80,
            "position": "Substitute",
            "subPosition": "Goalkeeper",
            "stat": [
              {
                "type": "formationPlace",
                "value": "0"
              }
            ]
          },
          {
            "playerId": "8ai99ucxjtl4gu5mejpjo4hlg",
            "firstName": "Caden",
            "lastName": "Trestrail",
            "shortFirstName": "Caden",
            "shortLastName": "Trestrail",
            "matchName": "C. Trestrail",
            "shirtNumber": 23,
            "position": "Substitute",
            "subPosition": "Midfielder",
            "stat": [
              {
                "type": "formationPlace",
                "value": "0"
              }
            ]
          }
        ],
        "teamOfficial": [
          {
            "id": "3ndh3g49duth6muzvigr2w2xh",
            "firstName": "Devorn",
            "lastName": "Jorsling",
            "shortFirstName": "Devorn",
            "shortLastName": "Jorsling",
            "type": "manager"
          }
        ],
        "stat": [
          {
            "fh": "164",
            "sh": "212",
            "type": "accuratePass",
            "value": "376"
          },
          {
            "fh": "1",
            "sh": "3",
            "type": "blockedScoringAtt",
            "value": "4"
          },
          {
            "fh": "0",
            "sh": "1",
            "type": "cornerTaken",
            "value": "1"
          },
          {
            "fh": "8",
            "sh": "5",
            "type": "fkFoulLost",
            "value": "13"
          },
          {
            "fh": "7",
            "sh": "6",
            "type": "fkFoulWon",
            "value": "13"
          },
          {
            "fh": "4",
            "sh": "4",
            "type": "goalKicks",
            "value": "8"
          },
          {
            "fh": "0",
            "sh": "1",
            "type": "goals",
            "value": "1"
          },
          {
            "fh": "2",
            "sh": "3",
            "type": "goalsConceded",
            "value": "5"
          },
          {
            "fh": "2",
            "sh": "2",
            "type": "lostCorners",
            "value": "4"
          },
          {
            "fh": "0",
            "sh": "3",
            "type": "ontargetScoringAtt",
            "value": "3"
          },
          {
            "fh": "54.2",
            "sh": "64.4",
            "type": "possessionPercentage",
            "value": "59.5"
          },
          {
            "fh": "2",
            "sh": "2",
            "type": "saves",
            "value": "4"
          },
          {
            "fh": "3",
            "sh": "1",
            "type": "shotOffTarget",
            "value": "4"
          },
          {
            "fh": "0",
            "sh": "5",
            "type": "subsMade",
            "value": "5"
          },
          {
            "fh": "9",
            "sh": "8",
            "type": "totalClearance",
            "value": "17"
          },
          {
            "fh": "0",
            "sh": "2",
            "type": "totalOffside",
            "value": "2"
          },
          {
            "fh": "197",
            "sh": "258",
            "type": "totalPass",
            "value": "455"
          },
          {
            "fh": "4",
            "sh": "7",
            "type": "totalScoringAtt",
            "value": "11"
          },
          {
            "fh": "6",
            "sh": "8",
            "type": "totalTackle",
            "value": "14"
          },
          {
            "fh": "8",
            "sh": "10",
            "type": "totalThrows",
            "value": "18"
          },
          {
            "fh": "2",
            "sh": "3",
            "type": "totalYellowCard",
            "value": "5"
          },
          {
            "fh": "0",
            "sh": "1",
            "type": "wonCorners",
            "value": "1"
          },
          {
            "fh": "4",
            "sh": "6",
            "type": "wonTackle",
            "value": "10"
          },
          {
            "type": "formationUsed",
            "value": "4231"
          }
        ],
        "kit": {
          "id": "31835",
          "colour1": "#FFFF00",
          "colour2": "#0000FF",
          "type": "home"
        }
      },
      {
        "contestantId": "34xm0flo8kh6skplqk4qybmui",
        "formationUsed": "4141",
        "player": [
          {
            "playerId": "4itogi9qw43hz23xi4hfyu82y",
            "firstName": "Tafari Hiziya",
            "lastName": "Chambers",
            "shortFirstName": "Tafari",
            "shortLastName": "Chambers",
            "matchName": "T. Chambers",
            "shirtNumber": 1,
            "position": "Goalkeeper",
            "positionSide": "Centre",
            "formationPlace": "1",
            "stat": [
              {
                "type": "accuratePass",
                "value": "10"
              },
              {
                "type": "gameStarted",
                "value": "1"
              },
              {
                "type": "goalKicks",
                "value": "7"
              },
              {
                "type": "goalsConceded",
                "value": "1"
              },
              {
                "type": "minsPlayed",
                "value": "90"
              },
              {
                "type": "saves",
                "value": "2"
              },
              {
                "type": "totalClearance",
                "value": "1"
              },
              {
                "type": "totalPass",
                "value": "14"
              },
              {
                "type": "formationPlace",
                "value": "1"
              }
            ]
          },
          {
            "playerId": "854wvptw9qrm30peuykvmv2wa",
            "firstName": "Kimoni Travolta Everton",
            "lastName": "Bailey",
            "shortFirstName": "Kimoni",
            "shortLastName": "Bailey",
            "matchName": "K. Bailey",
            "shirtNumber": 12,
            "position": "Defender",
            "positionSide": "Left",
            "formationPlace": "3",
            "stat": [
              {
                "type": "accuratePass",
                "value": "15"
              },
              {
                "type": "blockedScoringAtt",
                "value": "1"
              },
              {
                "type": "cornerTaken",
                "value": "1"
              },
              {
                "type": "gameStarted",
                "value": "1"
              },
              {
                "type": "goals",
                "value": "1"
              },
              {
                "type": "goalsConceded",
                "value": "1"
              },
              {
                "type": "minsPlayed",
                "value": "90"
              },
              {
                "type": "ontargetScoringAtt",
                "value": "1"
              },
              {
                "type": "shotOffTarget",
                "value": "1"
              },
              {
                "type": "totalPass",
                "value": "19"
              },
              {
                "type": "totalScoringAtt",
                "value": "3"
              },
              {
                "type": "totalTackle",
                "value": "2"
              },
              {
                "type": "totalThrows",
                "value": "9"
              },
              {
                "type": "wasFouled",
                "value": "1"
              },
              {
                "type": "wonCorners",
                "value": "2"
              },
              {
                "type": "wonTackle",
                "value": "1"
              },
              {
                "type": "formationPlace",
                "value": "3"
              }
            ]
          },
          {
            "playerId": "1m2glt59umfhzrf2kgdhppnmx",
            "firstName": "Jamoi Wade",
            "lastName": "Topey",
            "shortFirstName": "Jamoi",
            "shortLastName": "Topey",
            "matchName": "J. Topey",
            "shirtNumber": 42,
            "position": "Defender",
            "positionSide": "Left/Centre",
            "formationPlace": "6",
            "stat": [
              {
                "type": "accuratePass",
                "value": "26"
              },
              {
                "type": "fouls",
                "value": "1"
              },
              {
                "type": "gameStarted",
                "value": "1"
              },
              {
                "type": "goalAssist",
                "value": "1"
              },
              {
                "type": "goalKicks",
                "value": "2"
              },
              {
                "type": "goalsConceded",
                "value": "1"
              },
              {
                "type": "minsPlayed",
                "value": "90"
              },
              {
                "type": "totalClearance",
                "value": "4"
              },
              {
                "type": "totalPass",
                "value": "34"
              },
              {
                "type": "totalTackle",
                "value": "1"
              },
              {
                "type": "wonTackle",
                "value": "1"
              },
              {
                "type": "formationPlace",
                "value": "6"
              }
            ]
          },
          {
            "playerId": "4yk4fvry4w7njc599h5qog3kk",
            "firstName": "Fitzroy Alex",
            "lastName": "Cummings",
            "shortFirstName": "Fitzroy",
            "shortLastName": "Cummings",
            "matchName": "F. Cummings",
            "shirtNumber": 4,
            "position": "Defender",
            "positionSide": "Centre/Right",
            "formationPlace": "5",
            "stat": [
              {
                "type": "accuratePass",
                "value": "26"
              },
              {
                "type": "gameStarted",
                "value": "1"
              },
              {
                "type": "goalKicks",
                "value": "1"
              },
              {
                "type": "goalsConceded",
                "value": "1"
              },
              {
                "type": "minsPlayed",
                "value": "90"
              },
              {
                "type": "totalClearance",
                "value": "3"
              },
              {
                "type": "totalPass",
                "value": "37"
              },
              {
                "type": "totalTackle",
                "value": "3"
              },
              {
                "type": "wonTackle",
                "value": "2"
              },
              {
                "type": "formationPlace",
                "value": "5"
              }
            ]
          },
          {
            "playerId": "5mkfw3587qj2kd57yk619tcoa",
            "firstName": "Demario Rhoul Wrayton",
            "lastName": "Phillips",
            "shortFirstName": "Demario",
            "shortLastName": "Phillips",
            "matchName": "D. Phillips",
            "shirtNumber": 31,
            "position": "Defender",
            "positionSide": "Right",
            "formationPlace": "2",
            "stat": [
              {
                "type": "accuratePass",
                "value": "26"
              },
              {
                "type": "cornerTaken",
                "value": "1"
              },
              {
                "type": "fouls",
                "value": "3"
              },
              {
                "type": "gameStarted",
                "value": "1"
              },
              {
                "type": "goalsConceded",
                "value": "1"
              },
              {
                "type": "minsPlayed",
                "value": "90"
              },
              {
                "type": "shotOffTarget",
                "value": "1"
              },
              {
                "type": "totalClearance",
                "value": "1"
              },
              {
                "type": "totalPass",
                "value": "42"
              },
              {
                "type": "totalScoringAtt",
                "value": "1"
              },
              {
                "type": "totalTackle",
                "value": "5"
              },
              {
                "type": "totalThrows",
                "value": "10"
              },
              {
                "type": "wasFouled",
                "value": "4"
              },
              {
                "type": "wonTackle",
                "value": "2"
              },
              {
                "type": "formationPlace",
                "value": "2"
              }
            ]
          },
          {
            "playerId": "4pcwwhx1q9z84bvlnl7rml05w",
            "firstName": "Clifford",
            "lastName": "Thomas",
            "shortFirstName": "Clifford",
            "shortLastName": "Thomas",
            "matchName": "C. Thomas",
            "shirtNumber": 26,
            "position": "Defensive Midfielder",
            "positionSide": "Centre",
            "formationPlace": "4",
            "stat": [
              {
                "type": "accuratePass",
                "value": "27"
              },
              {
                "type": "fouls",
                "value": "1"
              },
              {
                "type": "gameStarted",
                "value": "1"
              },
              {
                "type": "goalAssist",
                "value": "1"
              },
              {
                "type": "goalsConceded",
                "value": "1"
              },
              {
                "type": "minsPlayed",
                "value": "90"
              },
              {
                "type": "shotOffTarget",
                "value": "1"
              },
              {
                "type": "totalClearance",
                "value": "2"
              },
              {
                "type": "totalPass",
                "value": "31"
              },
              {
                "type": "totalScoringAtt",
                "value": "1"
              },
              {
                "type": "totalTackle",
                "value": "1"
              },
              {
                "type": "wasFouled",
                "value": "1"
              },
              {
                "type": "formationPlace",
                "value": "4"
              }
            ]
          },
          {
            "playerId": "19ycnmneiucdrc1fd9zwrf4rt",
            "firstName": "Daniel Michael",
            "lastName": "Green",
            "shortFirstName": "Daniel",
            "shortLastName": "Green",
            "matchName": "D. Green",
            "shirtNumber": 9,
            "position": "Midfielder",
            "positionSide": "Left",
            "formationPlace": "11",
            "captain": "yes",
            "stat": [
              {
                "type": "accuratePass",
                "value": "9"
              },
              {
                "type": "gameStarted",
                "value": "1"
              },
              {
                "type": "goalAssist",
                "value": "1"
              },
              {
                "type": "minsPlayed",
                "value": "62"
              },
              {
                "type": "ontargetScoringAtt",
                "value": "1"
              },
              {
                "type": "totalPass",
                "value": "11"
              },
              {
                "type": "totalScoringAtt",
                "value": "1"
              },
              {
                "type": "totalSubOff",
                "value": "1"
              },
              {
                "type": "wasFouled",
                "value": "2"
              },
              {
                "type": "formationPlace",
                "value": "11"
              }
            ]
          },
          {
            "playerId": "6vsmcwxvz6hvbex8cxi6um1as",
            "firstName": "Raheem",
            "lastName": "Edwards",
            "shortFirstName": "Raheem",
            "shortLastName": "Edwards",
            "matchName": "R. Edwards",
            "shirtNumber": 25,
            "position": "Midfielder",
            "positionSide": "Left/Centre",
            "formationPlace": "10",
            "stat": [
              {
                "type": "accuratePass",
                "value": "7"
              },
              {
                "type": "fouls",
                "value": "2"
              },
              {
                "type": "gameStarted",
                "value": "1"
              },
              {
                "type": "goals",
                "value": "2"
              },
              {
                "type": "minsPlayed",
                "value": "75"
              },
              {
                "type": "ontargetScoringAtt",
                "value": "3"
              },
              {
                "type": "shotOffTarget",
                "value": "2"
              },
              {
                "type": "totalPass",
                "value": "9"
              },
              {
                "type": "totalScoringAtt",
                "value": "5"
              },
              {
                "type": "totalSubOff",
                "value": "1"
              },
              {
                "type": "totalTackle",
                "value": "2"
              },
              {
                "type": "wasFouled",
                "value": "1"
              },
              {
                "type": "formationPlace",
                "value": "10"
              }
            ]
          },
          {
            "playerId": "61esp7ett8p66f2agq9nuryp6",
            "firstName": "Jahshaun Mustaf",
            "lastName": "Anglin",
            "shortFirstName": "Jahshaun",
            "shortLastName": "Anglin",
            "matchName": "J. Anglin",
            "shirtNumber": 17,
            "position": "Midfielder",
            "positionSide": "Centre/Right",
            "formationPlace": "8",
            "stat": [
              {
                "type": "accuratePass",
                "value": "25"
              },
              {
                "type": "blockedScoringAtt",
                "value": "1"
              },
              {
                "type": "fouls",
                "value": "2"
              },
              {
                "type": "gameStarted",
                "value": "1"
              },
              {
                "type": "minsPlayed",
                "value": "83"
              },
              {
                "type": "shotOffTarget",
                "value": "1"
              },
              {
                "type": "totalPass",
                "value": "27"
              },
              {
                "type": "totalScoringAtt",
                "value": "2"
              },
              {
                "type": "totalSubOff",
                "value": "1"
              },
              {
                "type": "totalTackle",
                "value": "2"
              },
              {
                "type": "wonTackle",
                "value": "2"
              },
              {
                "type": "formationPlace",
                "value": "8"
              }
            ]
          },
          {
            "playerId": "549bk4ar8s05kzy78wi86one2",
            "firstName": "Alexander Andre",
            "lastName": "Marshsall",
            "shortFirstName": "Alex",
            "shortLastName": "Marshall",
            "matchName": "A. Marshsall",
            "shirtNumber": 11,
            "position": "Midfielder",
            "positionSide": "Right",
            "formationPlace": "7",
            "stat": [
              {
                "type": "accuratePass",
                "value": "22"
              },
              {
                "type": "cornerTaken",
                "value": "1"
              },
              {
                "type": "gameStarted",
                "value": "1"
              },
              {
                "type": "minsPlayed",
                "value": "75"
              },
              {
                "type": "totalClearance",
                "value": "1"
              },
              {
                "type": "totalPass",
                "value": "28"
              },
              {
                "type": "totalSubOff",
                "value": "1"
              },
              {
                "type": "totalTackle",
                "value": "1"
              },
              {
                "type": "wonTackle",
                "value": "1"
              },
              {
                "type": "formationPlace",
                "value": "7"
              }
            ]
          },
          {
            "playerId": "edtj63dyxok9m949znhjh75sk",
            "firstName": "Warner Dwayne",
            "lastName": "Brown",
            "shortFirstName": "Warner",
            "shortLastName": "Brown",
            "matchName": "W. Brown",
            "shirtNumber": 19,
            "position": "Striker",
            "positionSide": "Centre",
            "formationPlace": "9",
            "stat": [
              {
                "type": "accuratePass",
                "value": "9"
              },
              {
                "type": "fouls",
                "value": "1"
              },
              {
                "type": "gameStarted",
                "value": "1"
              },
              {
                "type": "goalAssist",
                "value": "1"
              },
              {
                "type": "goals",
                "value": "1"
              },
              {
                "type": "minsPlayed",
                "value": "75"
              },
              {
                "type": "ontargetScoringAtt",
                "value": "1"
              },
              {
                "type": "shotOffTarget",
                "value": "3"
              },
              {
                "type": "totalOffside",
                "value": "1"
              },
              {
                "type": "totalPass",
                "value": "15"
              },
              {
                "type": "totalScoringAtt",
                "value": "4"
              },
              {
                "type": "totalSubOff",
                "value": "1"
              },
              {
                "type": "totalTackle",
                "value": "3"
              },
              {
                "type": "wasFouled",
                "value": "2"
              },
              {
                "type": "wonCorners",
                "value": "2"
              },
              {
                "type": "wonTackle",
                "value": "1"
              },
              {
                "type": "formationPlace",
                "value": "9"
              }
            ]
          },
          {
            "playerId": "7xbxhzaxnm9wwi8i0ww5nw67e",
            "firstName": "Shaqueil Edward George",
            "lastName": "Bradford",
            "shortFirstName": "Shaqueil",
            "shortLastName": "Bradford",
            "matchName": "S. Bradford",
            "shirtNumber": 38,
            "position": "Substitute",
            "subPosition": "Attacker",
            "stat": [
              {
                "type": "accuratePass",
                "value": "2"
              },
              {
                "type": "fouls",
                "value": "2"
              },
              {
                "type": "goals",
                "value": "1"
              },
              {
                "type": "goalsConceded",
                "value": "1"
              },
              {
                "type": "lostCorners",
                "value": "1"
              },
              {
                "type": "minsPlayed",
                "value": "15"
              },
              {
                "type": "ontargetScoringAtt",
                "value": "2"
              },
              {
                "type": "totalPass",
                "value": "5"
              },
              {
                "type": "totalScoringAtt",
                "value": "2"
              },
              {
                "type": "totalSubOn",
                "value": "1"
              },
              {
                "type": "wasFouled",
                "value": "1"
              },
              {
                "type": "formationPlace",
                "value": "0"
              }
            ]
          },
          {
            "playerId": "3mgieimb1sjgggk06uzpomfx0",
            "firstName": "Earl Devon",
            "lastName": "Dennis",
            "shortFirstName": "Earl",
            "shortLastName": "Dennis",
            "matchName": "E. Dennis",
            "shirtNumber": 5,
            "position": "Substitute",
            "subPosition": "Defender",
            "stat": [
              {
                "type": "formationPlace",
                "value": "0"
              }
            ]
          },
          {
            "playerId": "7hb4gk3zcnu3r13umxb7vqhhw",
            "firstName": "Jaheem",
            "lastName": "Douglas",
            "shortFirstName": "Jaheem",
            "shortLastName": "Douglas",
            "matchName": "J. Douglas",
            "shirtNumber": 22,
            "position": "Substitute",
            "subPosition": "Defender",
            "stat": [
              {
                "type": "formationPlace",
                "value": "0"
              }
            ]
          },
          {
            "playerId": "c9yxsfgo7rqc2ztttx9dwk9gp",
            "firstName": "Shaquille Anthony",
            "lastName": "Dyer",
            "shortFirstName": "Shaquille",
            "shortLastName": "Dyer",
            "matchName": "S. Dyer",
            "shirtNumber": 33,
            "position": "Substitute",
            "subPosition": "Defender",
            "stat": [
              {
                "type": "formationPlace",
                "value": "0"
              }
            ]
          },
          {
            "playerId": "cu94mp8nllo13dw4nr92x4zbp",
            "firstName": "Kemar Robert",
            "lastName": "Foster",
            "shortFirstName": "Kemar",
            "shortLastName": "Foster",
            "matchName": "K. Foster",
            "shirtNumber": 34,
            "position": "Substitute",
            "subPosition": "Goalkeeper",
            "stat": [
              {
                "type": "formationPlace",
                "value": "0"
              }
            ]
          },
          {
            "playerId": "5nz5i26odqajveymm7s84ybfu",
            "firstName": "Gadail William",
            "lastName": "Irving",
            "shortFirstName": "Gadail",
            "shortLastName": "Irving",
            "matchName": "G. Irving",
            "shirtNumber": 2,
            "position": "Substitute",
            "subPosition": "Defender",
            "stat": [
              {
                "type": "accuratePass",
                "value": "5"
              },
              {
                "type": "goalsConceded",
                "value": "1"
              },
              {
                "type": "minsPlayed",
                "value": "28"
              },
              {
                "type": "ontargetScoringAtt",
                "value": "1"
              },
              {
                "type": "totalPass",
                "value": "6"
              },
              {
                "type": "totalScoringAtt",
                "value": "1"
              },
              {
                "type": "totalSubOn",
                "value": "1"
              },
              {
                "type": "totalThrows",
                "value": "2"
              },
              {
                "type": "formationPlace",
                "value": "0"
              }
            ]
          },
          {
            "playerId": "acp1dlhdhxwyupmqcy4wnfj84",
            "firstName": "Owen Matthew",
            "lastName": "Jumpp",
            "shortFirstName": "Owen",
            "shortLastName": "Jumpp",
            "matchName": "O. Jumpp",
            "shirtNumber": 21,
            "position": "Substitute",
            "subPosition": "Midfielder",
            "stat": [
              {
                "type": "formationPlace",
                "value": "0"
              }
            ]
          },
          {
            "playerId": "2py7ki0xiqxg8aovuuwh3bxn8",
            "firstName": "Claver",
            "lastName": "Nugent",
            "shortFirstName": "Claver",
            "shortLastName": "Nugent",
            "matchName": "C. Nugent",
            "shirtNumber": 28,
            "position": "Substitute",
            "subPosition": "Defender",
            "stat": [
              {
                "type": "accuratePass",
                "value": "2"
              },
              {
                "type": "goalsConceded",
                "value": "1"
              },
              {
                "type": "minsPlayed",
                "value": "7"
              },
              {
                "type": "totalPass",
                "value": "2"
              },
              {
                "type": "totalSubOn",
                "value": "1"
              },
              {
                "type": "formationPlace",
                "value": "0"
              }
            ]
          },
          {
            "playerId": "11fnw0grmhiwnqc6xg7xjlasp",
            "firstName": "Tevin Andrae",
            "lastName": "Shaw",
            "shortFirstName": "Tevin",
            "shortLastName": "Shaw",
            "matchName": "T. Shaw",
            "shirtNumber": 18,
            "position": "Substitute",
            "subPosition": "Midfielder",
            "stat": [
              {
                "type": "accuratePass",
                "value": "7"
              },
              {
                "type": "fouls",
                "value": "1"
              },
              {
                "type": "goalsConceded",
                "value": "1"
              },
              {
                "type": "minsPlayed",
                "value": "15"
              },
              {
                "type": "totalClearance",
                "value": "2"
              },
              {
                "type": "totalPass",
                "value": "9"
              },
              {
                "type": "totalSubOn",
                "value": "1"
              },
              {
                "type": "totalTackle",
                "value": "1"
              },
              {
                "type": "formationPlace",
                "value": "0"
              }
            ]
          },
          {
            "playerId": "aci1ycl0srtdtrkrn8wsv0d0p",
            "firstName": "Chevaughn",
            "lastName": "Walsh",
            "shortFirstName": "Chevaughn",
            "shortLastName": "Walsh",
            "matchName": "C. Walsh",
            "shirtNumber": 8,
            "position": "Substitute",
            "subPosition": "Attacker",
            "stat": [
              {
                "type": "accuratePass",
                "value": "5"
              },
              {
                "type": "fouls",
                "value": "1"
              },
              {
                "type": "goalAssist",
                "value": "1"
              },
              {
                "type": "goalsConceded",
                "value": "1"
              },
              {
                "type": "minsPlayed",
                "value": "15"
              },
              {
                "type": "totalPass",
                "value": "8"
              },
              {
                "type": "totalSubOn",
                "value": "1"
              },
              {
                "type": "yellowCard",
                "value": "1"
              },
              {
                "type": "formationPlace",
                "value": "0"
              }
            ]
          },
          {
            "playerId": "cluixmvrd84ojtts5pvhl9444",
            "firstName": "Angelo",
            "lastName": "Éxilus",
            "shortFirstName": "Angelo",
            "shortLastName": "Éxilus",
            "matchName": "A. Éxilus",
            "shirtNumber": 77,
            "position": "Substitute",
            "subPosition": "Attacker",
            "stat": [
              {
                "type": "formationPlace",
                "value": "0"
              }
            ]
          }
        ],
        "teamOfficial": [
          {
            "id": "1z6u0ba90z5f01glw370brsnp",
            "firstName": "Theodore",
            "lastName": "Eccleston Whitmore",
            "shortFirstName": "Theodore",
            "shortLastName": "Whitmore",
            "type": "manager"
          }
        ],
        "stat": [
          {
            "fh": "121",
            "sh": "102",
            "type": "accuratePass",
            "value": "223"
          },
          {
            "fh": "2",
            "sh": "0",
            "type": "blockedScoringAtt",
            "value": "2"
          },
          {
            "fh": "2",
            "sh": "1",
            "type": "cornerTaken",
            "value": "3"
          },
          {
            "fh": "7",
            "sh": "7",
            "type": "fkFoulLost",
            "value": "14"
          },
          {
            "fh": "7",
            "sh": "5",
            "type": "fkFoulWon",
            "value": "12"
          },
          {
            "fh": "2",
            "sh": "3",
            "type": "goalAssist",
            "value": "5"
          },
          {
            "fh": "7",
            "sh": "3",
            "type": "goalKicks",
            "value": "10"
          },
          {
            "fh": "2",
            "sh": "3",
            "type": "goals",
            "value": "5"
          },
          {
            "fh": "0",
            "sh": "1",
            "type": "goalsConceded",
            "value": "1"
          },
          {
            "fh": "0",
            "sh": "1",
            "type": "lostCorners",
            "value": "1"
          },
          {
            "fh": "4",
            "sh": "5",
            "type": "ontargetScoringAtt",
            "value": "9"
          },
          {
            "fh": "45.8",
            "sh": "35.6",
            "type": "possessionPercentage",
            "value": "40.5"
          },
          {
            "fh": "0",
            "sh": "2",
            "type": "saves",
            "value": "2"
          },
          {
            "fh": "4",
            "sh": "5",
            "type": "shotOffTarget",
            "value": "9"
          },
          {
            "fh": "0",
            "sh": "1",
            "type": "subsGoals",
            "value": "1"
          },
          {
            "fh": "0",
            "sh": "5",
            "type": "subsMade",
            "value": "5"
          },
          {
            "fh": "4",
            "sh": "10",
            "type": "totalClearance",
            "value": "14"
          },
          {
            "fh": "1",
            "sh": "0",
            "type": "totalOffside",
            "value": "1"
          },
          {
            "fh": "158",
            "sh": "139",
            "type": "totalPass",
            "value": "297"
          },
          {
            "fh": "10",
            "sh": "10",
            "type": "totalScoringAtt",
            "value": "20"
          },
          {
            "fh": "11",
            "sh": "10",
            "type": "totalTackle",
            "value": "21"
          },
          {
            "fh": "9",
            "sh": "12",
            "type": "totalThrows",
            "value": "21"
          },
          {
            "fh": "0",
            "sh": "1",
            "type": "totalYellowCard",
            "value": "1"
          },
          {
            "fh": "2",
            "sh": "2",
            "type": "wonCorners",
            "value": "4"
          },
          {
            "fh": "6",
            "sh": "4",
            "type": "wonTackle",
            "value": "10"
          },
          {
            "type": "formationUsed",
            "value": "4141"
          }
        ],
        "kit": {
          "id": "31717",
          "colour1": "#0000CC",
          "colour2": "#FFFFFF",
          "type": "home"
        }
      }
    ],
    "matchDetailsExtra": {
      "attendance": "793",
      "matchOfficial": [
        {
          "id": "683nh6h7orwc1sf0q32stj9xw",
          "type": "Main",
          "firstName": "Adonis",
          "lastName": "Carrasco Garcia",
          "shortFirstName": "Adonis",
          "shortLastName": "Carrasco"
        },
        {
          "id": "3xngnfhob1wogaueqx6wb10yc",
          "type": "Assistant referee 1",
          "firstName": "Jose Miguel",
          "lastName": "Bare Milano",
          "shortFirstName": "Jose",
          "shortLastName": "Bare Milano"
        },
        {
          "id": "eyces21rk16s4akfpaymti044",
          "type": "Assistant referee 2",
          "firstName": "Lendy",
          "lastName": "Taveras",
          "shortFirstName": "Lendy",
          "shortLastName": "Taveras"
        },
        {
          "id": "70l0a2iqlfh9vsk7kvuqbuaz8",
          "type": "Fourth official",
          "firstName": "Jose",
          "lastName": "Corporan",
          "shortFirstName": "Jose",
          "shortLastName": "Corporan"
        },
        {
          "id": "bh1wx3zg1pqwa3iq4qv984yz8",
          "type": "Video Assistant Referee",
          "firstName": "Benjamin Michael",
          "lastName": "Whitty",
          "shortFirstName": "Benjamin",
          "shortLastName": "Whitty"
        },
        {
          "id": "c9cm01imq3a1aqzp305bvdtd5",
          "type": "Assistant VAR Official",
          "firstName": "Tristley",
          "lastName": "Bassue",
          "shortFirstName": "Tristley",
          "shortLastName": "Bassue"
        }
      ]
    }
  }
}