{
  "matchInfo": {
    "id": "6pbiq1zwid07vc6ksaz7vqu50",
    "coverageLevel": "13",
    "date": "2025-10-02Z",
    "time": "00:00:00Z",
    "localDate": "2025-10-01",
    "localTime": "20:00:00",
    "week": "5",
    "postMatch": "1",
    "numberOfPeriods": 2,
    "periodLength": 45,
    "lastUpdated": "2025-11-07T18:33:45Z",
    "description": "Weymouth Wales vs Cavalier",
    "sport": {
      "id": "289u5typ3vp4ifwh5thalohmq",
      "name": "Soccer"
    },
    "ruleset": {
      "id": "79plas4983031idr6vw83nuel",
      "name": "Men"
    },
    "competition": {
      "id": "e6ysw58xmvgh3zwg400zw565s",
      "name": "Concacaf Caribbean Cup",
      "knownName": "Concacaf Caribbean Cup",
      "competitionCode": "CAC",
      "competitionFormat": "International cup",
      "country": {
        "id": "7yfrmldo7ozpwui3n6wfcy1n9",
        "name": "N/C America"
      }
    },
    "tournamentCalendar": {
      "id": "bygi47fmsxgbzysjdf9u481lg",
      "startDate": "2025-08-20Z",
      "endDate": "2025-12-03Z",
      "name": "2025"
    },
    "stage": {
      "id": "bzd7rsbz5iezyxc4oc4x54jro",
      "formatId": "86p6pz5rcsdbz4cklvfwtzrv9",
      "startDate": "2025-08-20Z",
      "endDate": "2025-10-02Z",
      "name": "Group Stage"
    },
    "series": {
      "id": "bzvjje87vdpzyn1y453bqp72s",
      "horizontal": 2,
      "formatId": "ci6ciikoil0ifcuis37z8h7md",
      "name": "Group B"
    },
    "contestant": [
      {
        "id": "bq7fp65wuqi9o4y3spob07e18",
        "name": "Weymouth Wales",
        "shortName": "Wales",
        "officialName": "JADA Group Weymouth Wales",
        "code": "WEY",
        "position": "home",
        "country": {
          "id": "6s2kneg94h46sha1zdawibpj0",
          "name": "Barbados"
        }
      },
      {
        "id": "3v5e2q2vqn0fgqrbkz6dbfs3i",
        "name": "Cavalier",
        "shortName": "Cavalier",
        "officialName": "Cavalier FC",
        "code": "CAV",
        "position": "away",
        "country": {
          "id": "gimxu1vjwoa2xrecyd9gtyoc",
          "name": "Jamaica"
        }
      }
    ],
    "venue": {
      "id": "2jv9cq6o32lc0n1y73iseaj96",
      "neutral": "no",
      "longName": "BFA Technical Centre",
      "shortName": "BFA Technical Centre",
      "latitude": "13.091525000",
      "longitude": "-59.573043000"
    }
  },
  "liveData": {
    "matchDetails": {
      "periodId": 14,
      "matchStatus": "Played",
      "winner": "home",
      "matchLengthMin": 99,
      "matchLengthSec": 2,
      "period": [
        {
          "id": 1,
          "start": "2025-10-02T00:06:12Z",
          "end": "2025-10-02T00:53:45Z",
          "lengthMin": 47,
          "lengthSec": 33,
          "announcedInjuryTime": 120
        },
        {
          "id": 2,
          "start": "2025-10-02T01:09:07Z",
          "end": "2025-10-02T02:00:36Z",
          "lengthMin": 51,
          "lengthSec": 29,
          "announcedInjuryTime": 360
        }
      ],
      "scores": {
        "ht": {
          "home": 1,
          "away": 1
        },
        "ft": {
          "home": 2,
          "away": 1
        },
        "total": {
          "home": 2,
          "away": 1
        }
      }
    },
    "goal": [
      {
        "contestantId": "bq7fp65wuqi9o4y3spob07e18",
        "periodId": 1,
        "timeMin": 10,
        "timeMinSec": "9:27",
        "lastUpdated": "2025-10-02T00:16:26Z",
        "timestamp": "2025-10-02T00:15:40Z",
        "type": "G",
        "scorerId": "aeu5ty2smdzh6xuc3omg8edp1",
        "scorerName": "A. Lashley",
        "assistPlayerId": "vcmm1g5pzlnuuyf2yscqzii2",
        "assistPlayerName": "A. Applewhaite",
        "optaEventId": "2854493521",
        "homeScore": 1,
        "awayScore": 0
      },
      {
        "contestantId": "3v5e2q2vqn0fgqrbkz6dbfs3i",
        "periodId": 1,
        "timeMin": 13,
        "timeMinSec": "12:24",
        "lastUpdated": "2025-10-02T00:19:28Z",
        "timestamp": "2025-10-02T00:18:37Z",
        "type": "G",
        "scorerId": "6ahwcd5nabjpypluy0sp0xq1g",
        "scorerName": "D. Massicot",
        "assistPlayerId": "6dg3tt5ji9fo2i9kcaoyeiivo",
        "assistPlayerName": "R. Thomas",
        "optaEventId": "2854494797",
        "homeScore": 1,
        "awayScore": 1
      },
      {
        "contestantId": "bq7fp65wuqi9o4y3spob07e18",
        "periodId": 2,
        "timeMin": 93,
        "timeMinSec": "92:08",
        "lastUpdated": "2025-10-02T01:57:11Z",
        "timestamp": "2025-10-02T01:56:15Z",
        "type": "G",
        "scorerId": "6dvjnump93sunmqpyti0q7384",
        "scorerName": "R. Bynoe",
        "assistPlayerId": "vcmm1g5pzlnuuyf2yscqzii2",
        "assistPlayerName": "A. Applewhaite",
        "optaEventId": "2854524383",
        "homeScore": 2,
        "awayScore": 1
      }
    ],
    "card": [
      {
        "contestantId": "bq7fp65wuqi9o4y3spob07e18",
        "periodId": 1,
        "timeMin": 32,
        "timeMinSec": "31:06",
        "lastUpdated": "2025-10-02T00:37:25Z",
        "timestamp": "2025-10-02T00:37:18Z",
        "type": "YC",
        "playerId": "vcmm1g5pzlnuuyf2yscqzii2",
        "playerName": "A. Applewhaite",
        "optaEventId": "2854502339",
        "cardReason": "Foul"
      },
      {
        "contestantId": "3v5e2q2vqn0fgqrbkz6dbfs3i",
        "periodId": 1,
        "timeMin": 47,
        "timeMinSec": "46:01",
        "lastUpdated": "2025-10-02T00:52:23Z",
        "timestamp": "2025-10-02T00:52:13Z",
        "type": "YC",
        "playerId": "4tvgcktwprmzs756xkj0qr0no",
        "playerName": "M. Forbes",
        "optaEventId": "2854508729",
        "cardReason": "Foul"
      },
      {
        "contestantId": "bq7fp65wuqi9o4y3spob07e18",
        "periodId": 2,
        "timeMin": 67,
        "timeMinSec": "66:36",
        "lastUpdated": "2025-10-02T01:30:54Z",
        "timestamp": "2025-10-02T01:30:44Z",
        "type": "YC",
        "playerId": "7795zi0zif5v51azkz0k1eqy1",
        "playerName": "A. Hill",
        "optaEventId": "2854517737",
        "cardReason": "Foul"
      },
      {
        "contestantId": "bq7fp65wuqi9o4y3spob07e18",
        "periodId": 2,
        "timeMin": 89,
        "timeMinSec": "88:48",
        "lastUpdated": "2025-10-02T01:53:22Z",
        "timestamp": "2025-10-02T01:52:55Z",
        "type": "YC",
        "playerId": "j45i82hjy24uofylgdqlb9bd",
        "playerName": "K. Primus",
        "optaEventId": "2854523563",
        "cardReason": "Time wasting"
      }
    ],
    "substitute": [
      {
        "contestantId": "bq7fp65wuqi9o4y3spob07e18",
        "periodId": 2,
        "timeMin": 57,
        "timeMinSec": "56:55",
        "lastUpdated": "2025-10-02T01:21:10Z",
        "timestamp": "2025-10-02T01:21:02Z",
        "playerOnId": "cmsuegygnc4740s5xme31femt",
        "playerOnName": "S. Stewart",
        "playerOffId": "a53fya0p1jxvha91aw9x4bqei",
        "playerOffName": "E. Downey",
        "subReason": "Tactical"
      },
      {
        "contestantId": "bq7fp65wuqi9o4y3spob07e18",
        "periodId": 2,
        "timeMin": 58,
        "timeMinSec": "57:10",
        "lastUpdated": "2025-10-02T01:21:25Z",
        "timestamp": "2025-10-02T01:21:17Z",
        "playerOnId": "71fsdmdqgxuhci9zju56dyr1m",
        "playerOnName": "R. Trim",
        "playerOffId": "aeu5ty2smdzh6xuc3omg8edp1",
        "playerOffName": "A. Lashley",
        "subReason": "Tactical"
      },
      {
        "contestantId": "bq7fp65wuqi9o4y3spob07e18",
        "periodId": 2,
        "timeMin": 58,
        "timeMinSec": "57:16",
        "lastUpdated": "2025-10-02T01:21:31Z",
        "timestamp": "2025-10-02T01:21:23Z",
        "playerOnId": "6dvjnump93sunmqpyti0q7384",
        "playerOnName": "R. Bynoe",
        "playerOffId": "cm69ps1neho1tm6tobl1elm1h",
        "playerOffName": "R. Morris",
        "subReason": "Tactical"
      },
      {
        "contestantId": "3v5e2q2vqn0fgqrbkz6dbfs3i",
        "periodId": 2,
        "timeMin": 58,
        "timeMinSec": "57:20",
        "lastUpdated": "2025-10-02T01:22:13Z",
        "timestamp": "2025-10-02T01:21:28Z",
        "playerOnId": "c62hmju9q0mwqhpgsi2or5btg",
        "playerOnName": "S. Stein",
        "playerOffId": "2diwf88ji08brdp1mkkqtorh0",
        "playerOffName": "D. McKenzie",
        "subReason": "Tactical"
      },
      {
        "contestantId": "3v5e2q2vqn0fgqrbkz6dbfs3i",
        "periodId": 2,
        "timeMin": 58,
        "timeMinSec": "57:21",
        "lastUpdated": "2025-10-02T01:23:07Z",
        "timestamp": "2025-10-02T01:21:28Z",
        "playerOnId": "9py5kadlbjllnk306xobfvnys",
        "playerOnName": "A. Reid",
        "playerOffId": "6ahwcd5nabjpypluy0sp0xq1g",
        "playerOffName": "D. Massicot",
        "subReason": "Tactical"
      },
      {
        "contestantId": "3v5e2q2vqn0fgqrbkz6dbfs3i",
        "periodId": 2,
        "timeMin": 65,
        "timeMinSec": "64:12",
        "lastUpdated": "2025-10-02T01:28:42Z",
        "timestamp": "2025-10-02T01:28:19Z",
        "playerOnId": "7jh0w1u6tz8if336l3uuwqexg",
        "playerOnName": "L. Watson",
        "playerOffId": "6dg3tt5ji9fo2i9kcaoyeiivo",
        "playerOffName": "R. Thomas",
        "subReason": "Tactical"
      },
      {
        "contestantId": "3v5e2q2vqn0fgqrbkz6dbfs3i",
        "periodId": 2,
        "timeMin": 65,
        "timeMinSec": "64:18",
        "lastUpdated": "2025-10-02T01:28:30Z",
        "timestamp": "2025-10-02T01:28:25Z",
        "playerOnId": "a2neaouy9ii2cg7oi9m3bs8ru",
        "playerOnName": "C. James",
        "playerOffId": "61ybxaacy505gx6mp5luy0kmi",
        "playerOffName": "J. Rigters",
        "subReason": "Tactical"
      },
      {
        "contestantId": "bq7fp65wuqi9o4y3spob07e18",
        "periodId": 2,
        "timeMin": 66,
        "timeMinSec": "66:00",
        "lastUpdated": "2025-10-02T01:30:12Z",
        "timestamp": "2025-10-02T01:30:07Z",
        "playerOnId": "6h0g9fpel50udhcgkeubkvpey",
        "playerOnName": "N. Brathwaite",
        "playerOffId": "enkehti0bovv4es2fnpou5t61",
        "playerOffName": "R. Jules",
        "subReason": "Tactical"
      },
      {
        "contestantId": "bq7fp65wuqi9o4y3spob07e18",
        "periodId": 2,
        "timeMin": 83,
        "timeMinSec": "82:17",
        "lastUpdated": "2025-10-02T01:46:29Z",
        "timestamp": "2025-10-02T01:46:24Z",
        "playerOnId": "cktm71ddnrjp2hi5afs6dft3o",
        "playerOnName": "J. James",
        "playerOffId": "7sajot15gh8wc05wlp4hwad3p",
        "playerOffName": "R. Smith",
        "subReason": "Tactical"
      }
    ],
    "lineUp": [
      {
        "contestantId": "bq7fp65wuqi9o4y3spob07e18",
        "formationUsed": "4231",
        "player": [
          {
            "playerId": "j45i82hjy24uofylgdqlb9bd",
            "firstName": "Kishmar Ishmael",
            "lastName": "Primus",
            "shortFirstName": "Kishmar",
            "shortLastName": "Primus",
            "matchName": "K. Primus",
            "shirtNumber": 1,
            "position": "Goalkeeper",
            "positionSide": "Centre",
            "formationPlace": "1",
            "stat": [
              {
                "type": "accuratePass",
                "value": "22"
              },
              {
                "type": "gameStarted",
                "value": "1"
              },
              {
                "type": "goalKicks",
                "value": "10"
              },
              {
                "type": "goalsConceded",
                "value": "1"
              },
              {
                "type": "minsPlayed",
                "value": "90"
              },
              {
                "type": "saves",
                "value": "3"
              },
              {
                "type": "totalClearance",
                "value": "1"
              },
              {
                "type": "totalPass",
                "value": "29"
              },
              {
                "type": "yellowCard",
                "value": "1"
              },
              {
                "type": "formationPlace",
                "value": "1"
              }
            ]
          },
          {
            "playerId": "vcmm1g5pzlnuuyf2yscqzii2",
            "firstName": "Ackeel Kerry",
            "lastName": "Applewhaite",
            "shortFirstName": "Ackeel",
            "shortLastName": "Applewhaite",
            "knownName": "Ackeel Applewhaite",
            "matchName": "A. Applewhaite",
            "shirtNumber": 7,
            "position": "Defender",
            "positionSide": "Left",
            "formationPlace": "3",
            "stat": [
              {
                "type": "accuratePass",
                "value": "33"
              },
              {
                "type": "cornerTaken",
                "value": "1"
              },
              {
                "type": "fouls",
                "value": "2"
              },
              {
                "type": "gameStarted",
                "value": "1"
              },
              {
                "type": "goalAssist",
                "value": "2"
              },
              {
                "type": "goalsConceded",
                "value": "1"
              },
              {
                "type": "minsPlayed",
                "value": "90"
              },
              {
                "type": "totalClearance",
                "value": "4"
              },
              {
                "type": "totalPass",
                "value": "48"
              },
              {
                "type": "totalTackle",
                "value": "1"
              },
              {
                "type": "totalThrows",
                "value": "8"
              },
              {
                "type": "yellowCard",
                "value": "1"
              },
              {
                "type": "formationPlace",
                "value": "3"
              }
            ]
          },
          {
            "playerId": "7795zi0zif5v51azkz0k1eqy1",
            "firstName": "Akeem Elvis",
            "lastName": "Hill",
            "shortFirstName": "Akeem",
            "shortLastName": "Hill",
            "matchName": "A. Hill",
            "shirtNumber": 6,
            "position": "Defender",
            "positionSide": "Left/Centre",
            "formationPlace": "6",
            "stat": [
              {
                "type": "accuratePass",
                "value": "36"
              },
              {
                "type": "fouls",
                "value": "2"
              },
              {
                "type": "gameStarted",
                "value": "1"
              },
              {
                "type": "goalsConceded",
                "value": "1"
              },
              {
                "type": "lostCorners",
                "value": "1"
              },
              {
                "type": "minsPlayed",
                "value": "90"
              },
              {
                "type": "shotOffTarget",
                "value": "1"
              },
              {
                "type": "totalClearance",
                "value": "8"
              },
              {
                "type": "totalOffside",
                "value": "1"
              },
              {
                "type": "totalPass",
                "value": "44"
              },
              {
                "type": "totalScoringAtt",
                "value": "1"
              },
              {
                "type": "wasFouled",
                "value": "1"
              },
              {
                "type": "yellowCard",
                "value": "1"
              },
              {
                "type": "formationPlace",
                "value": "6"
              }
            ]
          },
          {
            "playerId": "37r26oms3xmltsz489e3q8u7d",
            "firstName": "Mario Oneal",
            "lastName": "Williams",
            "shortFirstName": "Mario",
            "shortLastName": "Williams",
            "knownName": "Mario Williams",
            "matchName": "M. Williams",
            "shirtNumber": 19,
            "position": "Defender",
            "positionSide": "Centre/Right",
            "formationPlace": "5",
            "stat": [
              {
                "type": "accuratePass",
                "value": "35"
              },
              {
                "type": "blockedScoringAtt",
                "value": "1"
              },
              {
                "type": "fouls",
                "value": "1"
              },
              {
                "type": "gameStarted",
                "value": "1"
              },
              {
                "type": "goalKicks",
                "value": "5"
              },
              {
                "type": "goalsConceded",
                "value": "1"
              },
              {
                "type": "minsPlayed",
                "value": "90"
              },
              {
                "type": "totalClearance",
                "value": "7"
              },
              {
                "type": "totalPass",
                "value": "48"
              },
              {
                "type": "totalScoringAtt",
                "value": "1"
              },
              {
                "type": "totalThrows",
                "value": "5"
              },
              {
                "type": "wasFouled",
                "value": "1"
              },
              {
                "type": "formationPlace",
                "value": "5"
              }
            ]
          },
          {
            "playerId": "cm69ps1neho1tm6tobl1elm1h",
            "firstName": "Ricardio Owen",
            "lastName": "Morris",
            "shortFirstName": "Ricardio",
            "shortLastName": "Morris",
            "matchName": "R. Morris",
            "shirtNumber": 2,
            "position": "Defender",
            "positionSide": "Right",
            "formationPlace": "2",
            "stat": [
              {
                "type": "accuratePass",
                "value": "16"
              },
              {
                "type": "gameStarted",
                "value": "1"
              },
              {
                "type": "goalsConceded",
                "value": "1"
              },
              {
                "type": "lostCorners",
                "value": "1"
              },
              {
                "type": "minsPlayed",
                "value": "58"
              },
              {
                "type": "totalClearance",
                "value": "4"
              },
              {
                "type": "totalPass",
                "value": "23"
              },
              {
                "type": "totalSubOff",
                "value": "1"
              },
              {
                "type": "totalTackle",
                "value": "1"
              },
              {
                "type": "totalThrows",
                "value": "2"
              },
              {
                "type": "wonTackle",
                "value": "1"
              },
              {
                "type": "formationPlace",
                "value": "2"
              }
            ]
          },
          {
            "playerId": "9ov2mdh0kwk8qzkkzihm1snvt",
            "firstName": "Hadan Anderson",
            "lastName": "Holligan",
            "shortFirstName": "Hadan",
            "shortLastName": "Holligan",
            "matchName": "H. Holligan",
            "shirtNumber": 4,
            "position": "Defensive Midfielder",
            "positionSide": "Left/Centre",
            "formationPlace": "4",
            "captain": "yes",
            "stat": [
              {
                "type": "accuratePass",
                "value": "16"
              },
              {
                "type": "fouls",
                "value": "2"
              },
              {
                "type": "gameStarted",
                "value": "1"
              },
              {
                "type": "goalsConceded",
                "value": "1"
              },
              {
                "type": "minsPlayed",
                "value": "90"
              },
              {
                "type": "totalClearance",
                "value": "2"
              },
              {
                "type": "totalPass",
                "value": "18"
              },
              {
                "type": "totalTackle",
                "value": "2"
              },
              {
                "type": "wasFouled",
                "value": "4"
              },
              {
                "type": "wonTackle",
                "value": "1"
              },
              {
                "type": "formationPlace",
                "value": "4"
              }
            ]
          },
          {
            "playerId": "7sajot15gh8wc05wlp4hwad3p",
            "firstName": "Rashad Jamaal",
            "lastName": "Smith",
            "shortFirstName": "Rashad",
            "shortLastName": "Smith",
            "matchName": "R. Smith",
            "shirtNumber": 18,
            "position": "Defensive Midfielder",
            "positionSide": "Centre/Right",
            "formationPlace": "8",
            "stat": [
              {
                "type": "accuratePass",
                "value": "18"
              },
              {
                "type": "gameStarted",
                "value": "1"
              },
              {
                "type": "goalsConceded",
                "value": "1"
              },
              {
                "type": "minsPlayed",
                "value": "83"
              },
              {
                "type": "totalClearance",
                "value": "6"
              },
              {
                "type": "totalPass",
                "value": "28"
              },
              {
                "type": "totalSubOff",
                "value": "1"
              },
              {
                "type": "totalTackle",
                "value": "1"
              },
              {
                "type": "totalThrows",
                "value": "2"
              },
              {
                "type": "wasFouled",
                "value": "1"
              },
              {
                "type": "wonCorners",
                "value": "2"
              },
              {
                "type": "wonTackle",
                "value": "1"
              },
              {
                "type": "formationPlace",
                "value": "8"
              }
            ]
          },
          {
            "playerId": "a53fya0p1jxvha91aw9x4bqei",
            "firstName": "Elijah Rashid",
            "lastName": "Downey",
            "shortFirstName": "Elijah",
            "shortLastName": "Downey",
            "matchName": "E. Downey",
            "shirtNumber": 16,
            "position": "Attacking Midfielder",
            "positionSide": "Left",
            "formationPlace": "11",
            "stat": [
              {
                "type": "accuratePass",
                "value": "19"
              },
              {
                "type": "gameStarted",
                "value": "1"
              },
              {
                "type": "goalsConceded",
                "value": "1"
              },
              {
                "type": "minsPlayed",
                "value": "57"
              },
              {
                "type": "ontargetScoringAtt",
                "value": "1"
              },
              {
                "type": "shotOffTarget",
                "value": "1"
              },
              {
                "type": "totalPass",
                "value": "23"
              },
              {
                "type": "totalScoringAtt",
                "value": "2"
              },
              {
                "type": "totalSubOff",
                "value": "1"
              },
              {
                "type": "totalThrows",
                "value": "1"
              },
              {
                "type": "wasFouled",
                "value": "1"
              },
              {
                "type": "formationPlace",
                "value": "11"
              }
            ]
          },
          {
            "playerId": "6m5qe4kt6q3o06ead2798jw0l",
            "firstName": "Romario",
            "lastName": "Harewood",
            "shortFirstName": "Romario",
            "shortLastName": "Harewood",
            "matchName": "R. Harewood",
            "shirtNumber": 8,
            "position": "Attacking Midfielder",
            "positionSide": "Centre",
            "formationPlace": "10",
            "stat": [
              {
                "type": "accuratePass",
                "value": "23"
              },
              {
                "type": "cornerTaken",
                "value": "1"
              },
              {
                "type": "gameStarted",
                "value": "1"
              },
              {
                "type": "goalsConceded",
                "value": "1"
              },
              {
                "type": "minsPlayed",
                "value": "90"
              },
              {
                "type": "shotOffTarget",
                "value": "1"
              },
              {
                "type": "totalPass",
                "value": "32"
              },
              {
                "type": "totalScoringAtt",
                "value": "1"
              },
              {
                "type": "totalTackle",
                "value": "2"
              },
              {
                "type": "totalThrows",
                "value": "1"
              },
              {
                "type": "wasFouled",
                "value": "2"
              },
              {
                "type": "wonCorners",
                "value": "1"
              },
              {
                "type": "wonTackle",
                "value": "1"
              },
              {
                "type": "formationPlace",
                "value": "10"
              }
            ]
          },
          {
            "playerId": "enkehti0bovv4es2fnpou5t61",
            "firstName": "Rashad",
            "lastName": "Jules",
            "shortFirstName": "Rashad",
            "shortLastName": "Jules",
            "matchName": "R. Jules",
            "shirtNumber": 23,
            "position": "Attacking Midfielder",
            "positionSide": "Right",
            "formationPlace": "7",
            "stat": [
              {
                "type": "accuratePass",
                "value": "3"
              },
              {
                "type": "blockedScoringAtt",
                "value": "1"
              },
              {
                "type": "cornerTaken",
                "value": "2"
              },
              {
                "type": "fouls",
                "value": "3"
              },
              {
                "type": "gameStarted",
                "value": "1"
              },
              {
                "type": "goalsConceded",
                "value": "1"
              },
              {
                "type": "minsPlayed",
                "value": "66"
              },
              {
                "type": "ontargetScoringAtt",
                "value": "1"
              },
              {
                "type": "totalPass",
                "value": "10"
              },
              {
                "type": "totalScoringAtt",
                "value": "2"
              },
              {
                "type": "totalSubOff",
                "value": "1"
              },
              {
                "type": "wasFouled",
                "value": "2"
              },
              {
                "type": "formationPlace",
                "value": "7"
              }
            ]
          },
          {
            "playerId": "aeu5ty2smdzh6xuc3omg8edp1",
            "firstName": "Armando Adriano",
            "lastName": "Lashley",
            "shortFirstName": "Armando",
            "shortLastName": "Lashley",
            "matchName": "A. Lashley",
            "shirtNumber": 9,
            "position": "Striker",
            "positionSide": "Centre",
            "formationPlace": "9",
            "stat": [
              {
                "type": "accuratePass",
                "value": "8"
              },
              {
                "type": "gameStarted",
                "value": "1"
              },
              {
                "type": "goals",
                "value": "1"
              },
              {
                "type": "goalsConceded",
                "value": "1"
              },
              {
                "type": "minsPlayed",
                "value": "58"
              },
              {
                "type": "ontargetScoringAtt",
                "value": "1"
              },
              {
                "type": "totalPass",
                "value": "10"
              },
              {
                "type": "totalScoringAtt",
                "value": "1"
              },
              {
                "type": "totalSubOff",
                "value": "1"
              },
              {
                "type": "formationPlace",
                "value": "9"
              }
            ]
          },
          {
            "playerId": "6h0g9fpel50udhcgkeubkvpey",
            "firstName": "Nicoli Davion Malyk",
            "lastName": "Brathwaite",
            "shortFirstName": "Nicoli",
            "shortLastName": "Brathwaite",
            "matchName": "N. Brathwaite",
            "shirtNumber": 26,
            "position": "Substitute",
            "subPosition": "Defender",
            "stat": [
              {
                "type": "accuratePass",
                "value": "3"
              },
              {
                "type": "fouls",
                "value": "1"
              },
              {
                "type": "minsPlayed",
                "value": "24"
              },
              {
                "type": "totalClearance",
                "value": "8"
              },
              {
                "type": "totalPass",
                "value": "4"
              },
              {
                "type": "totalSubOn",
                "value": "1"
              },
              {
                "type": "totalTackle",
                "value": "1"
              },
              {
                "type": "totalThrows",
                "value": "1"
              },
              {
                "type": "formationPlace",
                "value": "0"
              }
            ]
          },
          {
            "playerId": "6dvjnump93sunmqpyti0q7384",
            "firstName": "Rommel",
            "lastName": "Bynoe",
            "shortFirstName": "Rommel",
            "shortLastName": "Bynoe",
            "matchName": "R. Bynoe",
            "shirtNumber": 25,
            "position": "Substitute",
            "subPosition": "Midfielder",
            "stat": [
              {
                "type": "accuratePass",
                "value": "10"
              },
              {
                "type": "goals",
                "value": "1"
              },
              {
                "type": "minsPlayed",
                "value": "32"
              },
              {
                "type": "ontargetScoringAtt",
                "value": "1"
              },
              {
                "type": "totalClearance",
                "value": "1"
              },
              {
                "type": "totalPass",
                "value": "13"
              },
              {
                "type": "totalScoringAtt",
                "value": "1"
              },
              {
                "type": "totalSubOn",
                "value": "1"
              },
              {
                "type": "formationPlace",
                "value": "0"
              }
            ]
          },
          {
            "playerId": "cl769tpcx6nuq7n8rz1pjbefp",
            "firstName": "Kemar",
            "lastName": "Headley",
            "shortFirstName": "Kemar",
            "shortLastName": "Headley",
            "matchName": "K. Headley",
            "shirtNumber": 11,
            "position": "Substitute",
            "subPosition": "Attacker",
            "stat": [
              {
                "type": "formationPlace",
                "value": "0"
              }
            ]
          },
          {
            "playerId": "4rzgzyh8dz5bjz62602im37dg",
            "firstName": "Najee",
            "lastName": "Holder",
            "shortFirstName": "Najee",
            "shortLastName": "Holder",
            "matchName": "N. Holder",
            "shirtNumber": 21,
            "position": "Substitute",
            "subPosition": "Defender",
            "stat": [
              {
                "type": "formationPlace",
                "value": "0"
              }
            ]
          },
          {
            "playerId": "cktm71ddnrjp2hi5afs6dft3o",
            "firstName": "Jante Brenton Jr.",
            "lastName": "James",
            "shortFirstName": "Jante",
            "shortLastName": "James",
            "matchName": "J. James",
            "shirtNumber": 15,
            "position": "Substitute",
            "subPosition": "Attacker",
            "stat": [
              {
                "type": "accuratePass",
                "value": "1"
              },
              {
                "type": "minsPlayed",
                "value": "7"
              },
              {
                "type": "totalPass",
                "value": "1"
              },
              {
                "type": "totalSubOn",
                "value": "1"
              },
              {
                "type": "formationPlace",
                "value": "0"
              }
            ]
          },
          {
            "playerId": "a2h48mj5bws2q5v6lvh0gf0x6",
            "firstName": "Shaquan",
            "lastName": "Phillips",
            "shortFirstName": "Shaquan",
            "shortLastName": "Phillips",
            "matchName": "S. Phillips",
            "shirtNumber": 30,
            "position": "Substitute",
            "subPosition": "Goalkeeper",
            "stat": [
              {
                "type": "formationPlace",
                "value": "0"
              }
            ]
          },
          {
            "playerId": "3uh2ps3fckgrrnq2py52ag00k",
            "firstName": "Romario",
            "lastName": "Small",
            "shortFirstName": "Romario",
            "shortLastName": "Small",
            "matchName": "R. Small",
            "shirtNumber": 13,
            "position": "Substitute",
            "subPosition": "Defender",
            "stat": [
              {
                "type": "formationPlace",
                "value": "0"
              }
            ]
          },
          {
            "playerId": "cmsuegygnc4740s5xme31femt",
            "firstName": "Shaquille",
            "lastName": "Stewart",
            "shortFirstName": "Shaquille",
            "shortLastName": "Stewart",
            "matchName": "S. Stewart",
            "shirtNumber": 14,
            "position": "Substitute",
            "subPosition": "Attacker",
            "stat": [
              {
                "type": "accuratePass",
                "value": "4"
              },
              {
                "type": "minsPlayed",
                "value": "33"
              },
              {
                "type": "ontargetScoringAtt",
                "value": "1"
              },
              {
                "type": "shotOffTarget",
                "value": "1"
              },
              {
                "type": "totalClearance",
                "value": "3"
              },
              {
                "type": "totalPass",
                "value": "8"
              },
              {
                "type": "totalScoringAtt",
                "value": "2"
              },
              {
                "type": "totalSubOn",
                "value": "1"
              },
              {
                "type": "wasFouled",
                "value": "1"
              },
              {
                "type": "wonCorners",
                "value": "1"
              },
              {
                "type": "formationPlace",
                "value": "0"
              }
            ]
          },
          {
            "playerId": "71fsdmdqgxuhci9zju56dyr1m",
            "firstName": "Ranaldo",
            "lastName": "Trim",
            "shortFirstName": "Ranaldo",
            "shortLastName": "Trim",
            "matchName": "R. Trim",
            "shirtNumber": 27,
            "position": "Substitute",
            "subPosition": "Midfielder",
            "stat": [
              {
                "type": "accuratePass",
                "value": "6"
              },
              {
                "type": "minsPlayed",
                "value": "32"
              },
              {
                "type": "totalClearance",
                "value": "3"
              },
              {
                "type": "totalPass",
                "value": "6"
              },
              {
                "type": "totalSubOn",
                "value": "1"
              },
              {
                "type": "totalTackle",
                "value": "1"
              },
              {
                "type": "wonTackle",
                "value": "1"
              },
              {
                "type": "formationPlace",
                "value": "0"
              }
            ]
          },
          {
            "playerId": "59xhnmbex45ac73ygv7wmk0lw",
            "firstName": "Rasheed",
            "lastName": "Williams",
            "shortFirstName": "Rasheed",
            "shortLastName": "Williams",
            "knownName": "Rasheed Williams",
            "matchName": "R. Williams",
            "shirtNumber": 17,
            "position": "Substitute",
            "subPosition": "Attacker",
            "stat": [
              {
                "type": "formationPlace",
                "value": "0"
              }
            ]
          }
        ],
        "teamOfficial": [
          {
            "id": "2ehc25m3putkpjutqkz6qm6t",
            "firstName": "Asquith",
            "lastName": "Hamlett-Howell",
            "shortFirstName": "Asquith",
            "shortLastName": "Hamlett",
            "type": "manager"
          }
        ],
        "stat": [
          {
            "fh": "160",
            "sh": "93",
            "type": "accuratePass",
            "value": "253"
          },
          {
            "fh": "1",
            "sh": "1",
            "type": "blockedScoringAtt",
            "value": "2"
          },
          {
            "fh": "3",
            "sh": "1",
            "type": "cornerTaken",
            "value": "4"
          },
          {
            "fh": "4",
            "sh": "7",
            "type": "fkFoulLost",
            "value": "11"
          },
          {
            "fh": "8",
            "sh": "5",
            "type": "fkFoulWon",
            "value": "13"
          },
          {
            "fh": "1",
            "sh": "1",
            "type": "goalAssist",
            "value": "2"
          },
          {
            "fh": "6",
            "sh": "9",
            "type": "goalKicks",
            "value": "15"
          },
          {
            "fh": "1",
            "sh": "1",
            "type": "goals",
            "value": "2"
          },
          {
            "fh": "1",
            "sh": "0",
            "type": "goalsConceded",
            "value": "1"
          },
          {
            "fh": "1",
            "sh": "1",
            "type": "lostCorners",
            "value": "2"
          },
          {
            "fh": "1",
            "sh": "4",
            "type": "ontargetScoringAtt",
            "value": "5"
          },
          {
            "fh": "61.8",
            "sh": "47.1",
            "type": "possessionPercentage",
            "value": "55.2"
          },
          {
            "fh": "2",
            "sh": "1",
            "type": "saves",
            "value": "3"
          },
          {
            "fh": "1",
            "sh": "3",
            "type": "shotOffTarget",
            "value": "4"
          },
          {
            "fh": "0",
            "sh": "1",
            "type": "subsGoals",
            "value": "1"
          },
          {
            "fh": "0",
            "sh": "5",
            "type": "subsMade",
            "value": "5"
          },
          {
            "fh": "18",
            "sh": "29",
            "type": "totalClearance",
            "value": "47"
          },
          {
            "fh": "0",
            "sh": "1",
            "type": "totalOffside",
            "value": "1"
          },
          {
            "fh": "218",
            "sh": "127",
            "type": "totalPass",
            "value": "345"
          },
          {
            "fh": "3",
            "sh": "8",
            "type": "totalScoringAtt",
            "value": "11"
          },
          {
            "fh": "6",
            "sh": "3",
            "type": "totalTackle",
            "value": "9"
          },
          {
            "fh": "10",
            "sh": "10",
            "type": "totalThrows",
            "value": "20"
          },
          {
            "fh": "1",
            "sh": "2",
            "type": "totalYellowCard",
            "value": "3"
          },
          {
            "fh": "3",
            "sh": "1",
            "type": "wonCorners",
            "value": "4"
          },
          {
            "fh": "3",
            "sh": "2",
            "type": "wonTackle",
            "value": "5"
          },
          {
            "type": "formationUsed",
            "value": "4231"
          }
        ],
        "kit": {
          "id": "31982",
          "colour1": "#000000",
          "type": "home"
        }
      },
      {
        "contestantId": "3v5e2q2vqn0fgqrbkz6dbfs3i",
        "formationUsed": "3421",
        "player": [
          {
            "playerId": "dj2luqi4ropj82dyiqfe5xwq1",
            "firstName": "Jeadine Shemar",
            "lastName": "White",
            "shortFirstName": "Jeadine",
            "shortLastName": "White",
            "matchName": "J. White",
            "shirtNumber": 31,
            "position": "Goalkeeper",
            "positionSide": "Centre",
            "formationPlace": "1",
            "stat": [
              {
                "type": "accuratePass",
                "value": "8"
              },
              {
                "type": "gameStarted",
                "value": "1"
              },
              {
                "type": "goalKicks",
                "value": "6"
              },
              {
                "type": "goalsConceded",
                "value": "2"
              },
              {
                "type": "lostCorners",
                "value": "1"
              },
              {
                "type": "minsPlayed",
                "value": "90"
              },
              {
                "type": "saves",
                "value": "3"
              },
              {
                "type": "totalPass",
                "value": "18"
              },
              {
                "type": "formationPlace",
                "value": "1"
              }
            ]
          },
          {
            "playerId": "4tvgcktwprmzs756xkj0qr0no",
            "firstName": "Michael",
            "lastName": "Forbes",
            "shortFirstName": "Michael",
            "shortLastName": "Forbes",
            "matchName": "M. Forbes",
            "shirtNumber": 24,
            "position": "Defender",
            "positionSide": "Left/Centre",
            "formationPlace": "4",
            "stat": [
              {
                "type": "accuratePass",
                "value": "18"
              },
              {
                "type": "fouls",
                "value": "1"
              },
              {
                "type": "gameStarted",
                "value": "1"
              },
              {
                "type": "goalsConceded",
                "value": "2"
              },
              {
                "type": "minsPlayed",
                "value": "90"
              },
              {
                "type": "totalClearance",
                "value": "4"
              },
              {
                "type": "totalPass",
                "value": "24"
              },
              {
                "type": "totalThrows",
                "value": "4"
              },
              {
                "type": "yellowCard",
                "value": "1"
              },
              {
                "type": "formationPlace",
                "value": "4"
              }
            ]
          },
          {
            "playerId": "bz4ic81047au6rl9upkfsnyfo",
            "firstName": "Jeovanni Barrington",
            "lastName": "Laing",
            "shortFirstName": "Jeovanni",
            "shortLastName": "Laing",
            "matchName": "J. Laing",
            "shirtNumber": 6,
            "position": "Defender",
            "positionSide": "Centre",
            "formationPlace": "5",
            "captain": "yes",
            "stat": [
              {
                "type": "accuratePass",
                "value": "22"
              },
              {
                "type": "blockedScoringAtt",
                "value": "1"
              },
              {
                "type": "gameStarted",
                "value": "1"
              },
              {
                "type": "goalsConceded",
                "value": "2"
              },
              {
                "type": "lostCorners",
                "value": "1"
              },
              {
                "type": "minsPlayed",
                "value": "90"
              },
              {
                "type": "totalClearance",
                "value": "11"
              },
              {
                "type": "totalPass",
                "value": "34"
              },
              {
                "type": "totalScoringAtt",
                "value": "1"
              },
              {
                "type": "totalTackle",
                "value": "4"
              },
              {
                "type": "totalThrows",
                "value": "3"
              },
              {
                "type": "wasFouled",
                "value": "1"
              },
              {
                "type": "wonTackle",
                "value": "3"
              },
              {
                "type": "formationPlace",
                "value": "5"
              }
            ]
          },
          {
            "playerId": "5oik8scypit8d99o9kgecpn9w",
            "firstName": "Shamar",
            "lastName": "Watson",
            "shortFirstName": "Shamar",
            "shortLastName": "Watson",
            "matchName": "S. Watson",
            "shirtNumber": 4,
            "position": "Defender",
            "positionSide": "Centre/Right",
            "formationPlace": "6",
            "stat": [
              {
                "type": "accuratePass",
                "value": "24"
              },
              {
                "type": "gameStarted",
                "value": "1"
              },
              {
                "type": "goalsConceded",
                "value": "2"
              },
              {
                "type": "minsPlayed",
                "value": "90"
              },
              {
                "type": "totalClearance",
                "value": "4"
              },
              {
                "type": "totalPass",
                "value": "36"
              },
              {
                "type": "totalTackle",
                "value": "2"
              },
              {
                "type": "totalThrows",
                "value": "7"
              },
              {
                "type": "wasFouled",
                "value": "2"
              },
              {
                "type": "wonCorners",
                "value": "1"
              },
              {
                "type": "formationPlace",
                "value": "6"
              }
            ]
          },
          {
            "playerId": "dkkv4g3lwtejqoazanse0zjmc",
            "firstName": "Christopher Jowell",
            "lastName": "Ainsworth",
            "shortFirstName": "Christopher",
            "shortLastName": "Ainsworth",
            "matchName": "C. Ainsworth",
            "shirtNumber": 11,
            "position": "Midfielder",
            "positionSide": "Left",
            "formationPlace": "3",
            "stat": [
              {
                "type": "accuratePass",
                "value": "22"
              },
              {
                "type": "cornerTaken",
                "value": "1"
              },
              {
                "type": "fouls",
                "value": "1"
              },
              {
                "type": "gameStarted",
                "value": "1"
              },
              {
                "type": "goalsConceded",
                "value": "2"
              },
              {
                "type": "lostCorners",
                "value": "2"
              },
              {
                "type": "minsPlayed",
                "value": "90"
              },
              {
                "type": "shotOffTarget",
                "value": "2"
              },
              {
                "type": "totalClearance",
                "value": "1"
              },
              {
                "type": "totalOffside",
                "value": "2"
              },
              {
                "type": "totalPass",
                "value": "38"
              },
              {
                "type": "totalScoringAtt",
                "value": "2"
              },
              {
                "type": "totalThrows",
                "value": "4"
              },
              {
                "type": "formationPlace",
                "value": "3"
              }
            ]
          },
          {
            "playerId": "6dg3tt5ji9fo2i9kcaoyeiivo",
            "firstName": "Romarion Anthony",
            "lastName": "Thomas",
            "shortFirstName": "Romarion",
            "shortLastName": "Thomas",
            "matchName": "R. Thomas",
            "shirtNumber": 17,
            "position": "Midfielder",
            "positionSide": "Left/Centre",
            "formationPlace": "8",
            "stat": [
              {
                "type": "accuratePass",
                "value": "17"
              },
              {
                "type": "fouls",
                "value": "2"
              },
              {
                "type": "gameStarted",
                "value": "1"
              },
              {
                "type": "goalAssist",
                "value": "1"
              },
              {
                "type": "goalsConceded",
                "value": "1"
              },
              {
                "type": "minsPlayed",
                "value": "65"
              },
              {
                "type": "shotOffTarget",
                "value": "1"
              },
              {
                "type": "totalPass",
                "value": "18"
              },
              {
                "type": "totalScoringAtt",
                "value": "1"
              },
              {
                "type": "totalSubOff",
                "value": "1"
              },
              {
                "type": "totalTackle",
                "value": "2"
              },
              {
                "type": "wonTackle",
                "value": "1"
              },
              {
                "type": "formationPlace",
                "value": "8"
              }
            ]
          },
          {
            "playerId": "7mhox7ebowqbmbowmcu0olx0q",
            "firstName": "Dwayne Anthony",
            "lastName": "Allen",
            "shortFirstName": "Dwayne",
            "shortLastName": "Allen",
            "matchName": "D. Allen",
            "shirtNumber": 13,
            "position": "Midfielder",
            "positionSide": "Centre/Right",
            "formationPlace": "7",
            "stat": [
              {
                "type": "accuratePass",
                "value": "22"
              },
              {
                "type": "fouls",
                "value": "1"
              },
              {
                "type": "gameStarted",
                "value": "1"
              },
              {
                "type": "goalsConceded",
                "value": "2"
              },
              {
                "type": "minsPlayed",
                "value": "90"
              },
              {
                "type": "totalClearance",
                "value": "1"
              },
              {
                "type": "totalPass",
                "value": "28"
              },
              {
                "type": "totalTackle",
                "value": "3"
              },
              {
                "type": "wasFouled",
                "value": "1"
              },
              {
                "type": "wonTackle",
                "value": "3"
              },
              {
                "type": "formationPlace",
                "value": "7"
              }
            ]
          },
          {
            "playerId": "1gg3m6bdh2selr8ndf3s5gidw",
            "firstName": "Jerome",
            "lastName": "Zidon McLeary",
            "shortFirstName": "Jerome",
            "shortLastName": "McLeary",
            "matchName": "J. McLeary",
            "shirtNumber": 27,
            "position": "Midfielder",
            "positionSide": "Right",
            "formationPlace": "2",
            "stat": [
              {
                "type": "accuratePass",
                "value": "14"
              },
              {
                "type": "fouls",
                "value": "2"
              },
              {
                "type": "gameStarted",
                "value": "1"
              },
              {
                "type": "goalsConceded",
                "value": "2"
              },
              {
                "type": "minsPlayed",
                "value": "90"
              },
              {
                "type": "shotOffTarget",
                "value": "3"
              },
              {
                "type": "totalClearance",
                "value": "2"
              },
              {
                "type": "totalPass",
                "value": "21"
              },
              {
                "type": "totalScoringAtt",
                "value": "3"
              },
              {
                "type": "totalTackle",
                "value": "2"
              },
              {
                "type": "totalThrows",
                "value": "4"
              },
              {
                "type": "wasFouled",
                "value": "1"
              },
              {
                "type": "wonCorners",
                "value": "1"
              },
              {
                "type": "wonTackle",
                "value": "2"
              },
              {
                "type": "formationPlace",
                "value": "2"
              }
            ]
          },
          {
            "playerId": "2diwf88ji08brdp1mkkqtorh0",
            "firstName": "Denzel",
            "lastName": "McKenzie",
            "shortFirstName": "Denzel",
            "shortLastName": "Mckenzie",
            "matchName": "D. McKenzie",
            "shirtNumber": 12,
            "position": "Attacking Midfielder",
            "positionSide": "Left/Centre",
            "formationPlace": "11",
            "stat": [
              {
                "type": "accuratePass",
                "value": "10"
              },
              {
                "type": "cornerTaken",
                "value": "1"
              },
              {
                "type": "fouls",
                "value": "1"
              },
              {
                "type": "gameStarted",
                "value": "1"
              },
              {
                "type": "goalsConceded",
                "value": "1"
              },
              {
                "type": "minsPlayed",
                "value": "58"
              },
              {
                "type": "ontargetScoringAtt",
                "value": "1"
              },
              {
                "type": "totalPass",
                "value": "10"
              },
              {
                "type": "totalScoringAtt",
                "value": "1"
              },
              {
                "type": "totalSubOff",
                "value": "1"
              },
              {
                "type": "totalTackle",
                "value": "1"
              },
              {
                "type": "totalThrows",
                "value": "1"
              },
              {
                "type": "formationPlace",
                "value": "11"
              }
            ]
          },
          {
            "playerId": "61ybxaacy505gx6mp5luy0kmi",
            "firstName": "Jamilhio Ivar Clifton",
            "lastName": "Rigters",
            "shortFirstName": "Jamilhio",
            "shortLastName": "Rigters",
            "matchName": "J. Rigters",
            "shirtNumber": 10,
            "position": "Attacking Midfielder",
            "positionSide": "Centre/Right",
            "formationPlace": "10",
            "stat": [
              {
                "type": "accuratePass",
                "value": "11"
              },
              {
                "type": "fouls",
                "value": "1"
              },
              {
                "type": "gameStarted",
                "value": "1"
              },
              {
                "type": "goalsConceded",
                "value": "1"
              },
              {
                "type": "minsPlayed",
                "value": "65"
              },
              {
                "type": "totalClearance",
                "value": "2"
              },
              {
                "type": "totalPass",
                "value": "17"
              },
              {
                "type": "totalSubOff",
                "value": "1"
              },
              {
                "type": "totalTackle",
                "value": "3"
              },
              {
                "type": "totalThrows",
                "value": "4"
              },
              {
                "type": "wasFouled",
                "value": "3"
              },
              {
                "type": "wonTackle",
                "value": "2"
              },
              {
                "type": "formationPlace",
                "value": "10"
              }
            ]
          },
          {
            "playerId": "6ahwcd5nabjpypluy0sp0xq1g",
            "firstName": "Daryl Tyree",
            "lastName": "Massicot",
            "shortFirstName": "Daryl",
            "shortLastName": "Massicot",
            "matchName": "D. Massicot",
            "shirtNumber": 7,
            "position": "Striker",
            "positionSide": "Centre",
            "formationPlace": "9",
            "stat": [
              {
                "type": "accuratePass",
                "value": "6"
              },
              {
                "type": "blockedScoringAtt",
                "value": "1"
              },
              {
                "type": "fouls",
                "value": "3"
              },
              {
                "type": "gameStarted",
                "value": "1"
              },
              {
                "type": "goals",
                "value": "1"
              },
              {
                "type": "goalsConceded",
                "value": "1"
              },
              {
                "type": "minsPlayed",
                "value": "58"
              },
              {
                "type": "ontargetScoringAtt",
                "value": "2"
              },
              {
                "type": "shotOffTarget",
                "value": "1"
              },
              {
                "type": "totalOffside",
                "value": "3"
              },
              {
                "type": "totalPass",
                "value": "8"
              },
              {
                "type": "totalScoringAtt",
                "value": "4"
              },
              {
                "type": "totalSubOff",
                "value": "1"
              },
              {
                "type": "wasFouled",
                "value": "1"
              },
              {
                "type": "formationPlace",
                "value": "9"
              }
            ]
          },
          {
            "playerId": "85htkw4l7u0gomwp33oc9mpzo",
            "firstName": "Riquelme",
            "lastName": "Antomoi",
            "shortFirstName": "Riquelme",
            "shortLastName": "Antomoi",
            "matchName": "R. Antomoi",
            "shirtNumber": 21,
            "position": "Substitute",
            "subPosition": "Attacker",
            "stat": [
              {
                "type": "formationPlace",
                "value": "0"
              }
            ]
          },
          {
            "playerId": "1qior0wajtprqm33u9vlmfl2i",
            "firstName": "Deshawn",
            "lastName": "Bernard",
            "shortFirstName": "Deshawn",
            "shortLastName": "Bernard",
            "matchName": "D. Bernard",
            "shirtNumber": 18,
            "position": "Substitute",
            "subPosition": "Midfielder",
            "stat": [
              {
                "type": "formationPlace",
                "value": "0"
              }
            ]
          },
          {
            "playerId": "8oph9nnfgn967u8hseoq3cokq",
            "firstName": "Damelcio",
            "lastName": "Fer",
            "shortFirstName": "Damelcio",
            "shortLastName": "Fer",
            "matchName": "D. Fer",
            "shirtNumber": 40,
            "position": "Substitute",
            "subPosition": "Goalkeeper",
            "stat": [
              {
                "type": "formationPlace",
                "value": "0"
              }
            ]
          },
          {
            "playerId": "9vwqsm6xargzzvtnxh628uo7o",
            "firstName": "James",
            "lastName": "Gallimore",
            "shortFirstName": "James",
            "shortLastName": "Gallimore",
            "matchName": "J. Gallimore",
            "shirtNumber": 29,
            "position": "Substitute",
            "subPosition": "Attacker",
            "stat": [
              {
                "type": "formationPlace",
                "value": "0"
              }
            ]
          },
          {
            "playerId": "a2neaouy9ii2cg7oi9m3bs8ru",
            "firstName": "Chad Connor Christopher",
            "lastName": "James",
            "shortFirstName": "Chad",
            "shortLastName": "James",
            "matchName": "C. James",
            "shirtNumber": 19,
            "position": "Substitute",
            "subPosition": "Midfielder",
            "stat": [
              {
                "type": "accuratePass",
                "value": "2"
              },
              {
                "type": "goalsConceded",
                "value": "1"
              },
              {
                "type": "minsPlayed",
                "value": "25"
              },
              {
                "type": "shotOffTarget",
                "value": "1"
              },
              {
                "type": "totalClearance",
                "value": "1"
              },
              {
                "type": "totalPass",
                "value": "5"
              },
              {
                "type": "totalScoringAtt",
                "value": "1"
              },
              {
                "type": "totalSubOn",
                "value": "1"
              },
              {
                "type": "wasFouled",
                "value": "2"
              },
              {
                "type": "formationPlace",
                "value": "0"
              }
            ]
          },
          {
            "playerId": "9py5kadlbjllnk306xobfvnys",
            "firstName": "Adrian Ricardo",
            "lastName": "Reid Jr.",
            "shortFirstName": "Adrian",
            "shortLastName": "Reid",
            "knownName": "Adrian Reid",
            "matchName": "A. Reid",
            "shirtNumber": 8,
            "position": "Substitute",
            "subPosition": "Defender",
            "stat": [
              {
                "type": "accuratePass",
                "value": "9"
              },
              {
                "type": "fouls",
                "value": "2"
              },
              {
                "type": "goalsConceded",
                "value": "1"
              },
              {
                "type": "minsPlayed",
                "value": "32"
              },
              {
                "type": "totalPass",
                "value": "16"
              },
              {
                "type": "totalSubOn",
                "value": "1"
              },
              {
                "type": "totalTackle",
                "value": "1"
              },
              {
                "type": "totalThrows",
                "value": "3"
              },
              {
                "type": "wonTackle",
                "value": "1"
              },
              {
                "type": "formationPlace",
                "value": "0"
              }
            ]
          },
          {
            "playerId": "c62hmju9q0mwqhpgsi2or5btg",
            "firstName": "Shaquille Urekiel Dykimbe",
            "lastName": "Stein",
            "shortFirstName": "Shaquille",
            "shortLastName": "Stein",
            "matchName": "S. Stein",
            "shirtNumber": 33,
            "position": "Substitute",
            "subPosition": "Attacker",
            "stat": [
              {
                "type": "accuratePass",
                "value": "4"
              },
              {
                "type": "goalsConceded",
                "value": "1"
              },
              {
                "type": "minsPlayed",
                "value": "32"
              },
              {
                "type": "ontargetScoringAtt",
                "value": "1"
              },
              {
                "type": "totalPass",
                "value": "8"
              },
              {
                "type": "totalScoringAtt",
                "value": "1"
              },
              {
                "type": "totalSubOn",
                "value": "1"
              },
              {
                "type": "formationPlace",
                "value": "0"
              }
            ]
          },
          {
            "playerId": "252ht8l4n2vmusbr30etmwzkk",
            "firstName": "Deshawn Dontae",
            "lastName": "Talbert",
            "shortFirstName": "Deshawn",
            "shortLastName": "Talbert",
            "matchName": "D. Talbert",
            "shirtNumber": 5,
            "position": "Substitute",
            "subPosition": "Defender",
            "stat": [
              {
                "type": "formationPlace",
                "value": "0"
              }
            ]
          },
          {
            "playerId": "471ii23e0s6dyawda1yzmigic",
            "firstName": "Kwayne Troy",
            "lastName": "Thompson",
            "shortFirstName": "Kwayne",
            "shortLastName": "Thompson",
            "matchName": "K. Thompson",
            "shirtNumber": 23,
            "position": "Substitute",
            "subPosition": "Defender",
            "stat": [
              {
                "type": "formationPlace",
                "value": "0"
              }
            ]
          },
          {
            "playerId": "agdn4p1mokraf204b5xhy32ms",
            "firstName": "Garfield",
            "lastName": "Tomlinson",
            "shortFirstName": "Garfield",
            "shortLastName": "Tomlinson",
            "matchName": "G. Tomlinson",
            "shirtNumber": 50,
            "position": "Substitute",
            "subPosition": "Goalkeeper",
            "stat": [
              {
                "type": "formationPlace",
                "value": "0"
              }
            ]
          },
          {
            "playerId": "7jh0w1u6tz8if336l3uuwqexg",
            "firstName": "Luis Anthony Grant",
            "lastName": "Watson",
            "shortFirstName": "Luis",
            "shortLastName": "Watson",
            "matchName": "L. Watson",
            "shirtNumber": 22,
            "position": "Substitute",
            "subPosition": "Defender",
            "stat": [
              {
                "type": "accuratePass",
                "value": "4"
              },
              {
                "type": "goalsConceded",
                "value": "1"
              },
              {
                "type": "minsPlayed",
                "value": "25"
              },
              {
                "type": "shotOffTarget",
                "value": "1"
              },
              {
                "type": "totalClearance",
                "value": "1"
              },
              {
                "type": "totalPass",
                "value": "9"
              },
              {
                "type": "totalScoringAtt",
                "value": "1"
              },
              {
                "type": "totalSubOn",
                "value": "1"
              },
              {
                "type": "totalThrows",
                "value": "1"
              },
              {
                "type": "formationPlace",
                "value": "0"
              }
            ]
          }
        ],
        "teamOfficial": [
          {
            "id": "95wr9aggr1sdcagctkd8bko6i",
            "firstName": "Rudolph",
            "lastName": "Speid",
            "shortFirstName": "Rudolph",
            "shortLastName": "Speid",
            "type": "manager"
          }
        ],
        "stat": [
          {
            "fh": "96",
            "sh": "97",
            "type": "accuratePass",
            "value": "193"
          },
          {
            "fh": "1",
            "sh": "1",
            "type": "blockedScoringAtt",
            "value": "2"
          },
          {
            "fh": "1",
            "sh": "1",
            "type": "cornerTaken",
            "value": "2"
          },
          {
            "fh": "9",
            "sh": "5",
            "type": "fkFoulLost",
            "value": "14"
          },
          {
            "fh": "4",
            "sh": "7",
            "type": "fkFoulWon",
            "value": "11"
          },
          {
            "fh": "1",
            "sh": "0",
            "type": "goalAssist",
            "value": "1"
          },
          {
            "fh": "0",
            "sh": "6",
            "type": "goalKicks",
            "value": "6"
          },
          {
            "fh": "1",
            "sh": "0",
            "type": "goals",
            "value": "1"
          },
          {
            "fh": "1",
            "sh": "1",
            "type": "goalsConceded",
            "value": "2"
          },
          {
            "fh": "3",
            "sh": "1",
            "type": "lostCorners",
            "value": "4"
          },
          {
            "fh": "3",
            "sh": "1",
            "type": "ontargetScoringAtt",
            "value": "4"
          },
          {
            "fh": "38.2",
            "sh": "52.9",
            "type": "possessionPercentage",
            "value": "44.8"
          },
          {
            "fh": "0",
            "sh": "3",
            "type": "saves",
            "value": "3"
          },
          {
            "fh": "3",
            "sh": "6",
            "type": "shotOffTarget",
            "value": "9"
          },
          {
            "fh": "0",
            "sh": "4",
            "type": "subsMade",
            "value": "4"
          },
          {
            "fh": "13",
            "sh": "14",
            "type": "totalClearance",
            "value": "27"
          },
          {
            "fh": "3",
            "sh": "2",
            "type": "totalOffside",
            "value": "5"
          },
          {
            "fh": "137",
            "sh": "153",
            "type": "totalPass",
            "value": "290"
          },
          {
            "fh": "7",
            "sh": "8",
            "type": "totalScoringAtt",
            "value": "15"
          },
          {
            "fh": "7",
            "sh": "11",
            "type": "totalTackle",
            "value": "18"
          },
          {
            "fh": "21",
            "sh": "10",
            "type": "totalThrows",
            "value": "31"
          },
          {
            "fh": "1",
            "sh": "0",
            "type": "totalYellowCard",
            "value": "1"
          },
          {
            "fh": "1",
            "sh": "1",
            "type": "wonCorners",
            "value": "2"
          },
          {
            "fh": "3",
            "sh": "9",
            "type": "wonTackle",
            "value": "12"
          },
          {
            "type": "formationUsed",
            "value": "3421"
          }
        ],
        "kit": {
          "id": "23110",
          "colour1": "#FFFFFF",
          "type": "home"
        }
      }
    ],
    "matchDetailsExtra": {
      "matchOfficial": [
        {
          "id": "79ux87bamq38ooxrtacl9ln9w",
          "type": "Main",
          "firstName": "Khamal Vere Benjamin",
          "lastName": "Harding-Hodge",
          "shortFirstName": "Khamal",
          "shortLastName": "Harding-Hodge"
        },
        {
          "id": "7q2n29sncvhdqi73y4610lune",
          "type": "Assistant referee 1",
          "firstName": "Daniel",
          "lastName": "Clenton Harviel",
          "shortFirstName": "Clenton",
          "shortLastName": "Daniel"
        },
        {
          "id": "bq98qj1m9dqrhykstouy7x10q",
          "type": "Assistant referee 2",
          "firstName": "Kleon",
          "lastName": "Lindey",
          "shortFirstName": "Kleon",
          "shortLastName": "Lindey"
        },
        {
          "id": "70l0a2iqlfh9vsk7kvuqbuaz8",
          "type": "Fourth official",
          "firstName": "Jose",
          "lastName": "Corporan",
          "shortFirstName": "Jose",
          "shortLastName": "Corporan"
        }
      ]
    }
  }
}